[
    {
        "goals": "0",
        "shots": "0",
        "xG": "0",
        "time": "90",
        "position": "GK",
        "h_team": "Liverpool",
        "a_team": "Middlesbrough",
        "h_goals": "3",
        "a_goals": "0",
        "date": "2017-05-21",
        "id": "3515",
        "season": "2016",
        "roster_id": "125289",
        "xA": "0",
        "assists": "0",
        "key_passes": "0",
        "npg": "0",
        "npxG": "0",
        "xGChain": "0.3118875324726105",
        "xGBuildup": "0.3118875324726105"
    },
    {
        "goals": "0",
        "shots": "0",
        "xG": "0",
        "time": "90",
        "position": "GK",
        "h_team": "Middlesbrough",
        "a_team": "Southampton",
        "h_goals": "1",
        "a_goals": "2",
        "date": "2017-05-13",
        "id": "3504",
        "season": "2016",
        "roster_id": "135313",
        "xA": "0",
        "assists": "0",
        "key_passes": "0",
        "npg": "0",
        "npxG": "0",
        "xGChain": "0",
        "xGBuildup": "0"
    },
    {
        "goals": "0",
        "shots": "0",
        "xG": "0",
        "time": "90",
        "position": "GK",
        "h_team": "Chelsea",
        "a_team": "Middlesbrough",
        "h_goals": "3",
        "a_goals": "0",
        "date": "2017-05-08",
        "id": "3493",
        "season": "2016",
        "roster_id": "134856",
        "xA": "0",
        "assists": "0",
        "key_passes": "0",
        "npg": "0",
        "npxG": "0",
        "xGChain": "0.009306610561907291",
        "xGBuildup": "0.009306610561907291"
    },
    {
        "goals": "0",
        "shots": "0",
        "xG": "0",
        "time": "90",
        "position": "GK",
        "h_team": "Middlesbrough",
        "a_team": "Manchester City",
        "h_goals": "2",
        "a_goals": "2",
        "date": "2017-04-30",
        "id": "3483",
        "season": "2016",
        "roster_id": "134429",
        "xA": "0",
        "assists": "0",
        "key_passes": "0",
        "npg": "0",
        "npxG": "0",
        "xGChain": "0",
        "xGBuildup": "0"
    },
    {
        "goals": "0",
        "shots": "0",
        "xG": "0",
        "time": "90",
        "position": "GK",
        "h_team": "Middlesbrough",
        "a_team": "Sunderland",
        "h_goals": "1",
        "a_goals": "0",
        "date": "2017-04-26",
        "id": "3413",
        "season": "2016",
        "roster_id": "132839",
        "xA": "0",
        "assists": "0",
        "key_passes": "0",
        "npg": "0",
        "npxG": "0",
        "xGChain": "0",
        "xGBuildup": "0"
    },
    {
        "goals": "0",
        "shots": "0",
        "xG": "0",
        "time": "90",
        "position": "GK",
        "h_team": "Bournemouth",
        "a_team": "Middlesbrough",
        "h_goals": "4",
        "a_goals": "0",
        "date": "2017-04-22",
        "id": "3471",
        "season": "2016",
        "roster_id": "135159",
        "xA": "0",
        "assists": "0",
        "key_passes": "0",
        "npg": "0",
        "npxG": "0",
        "xGChain": "0",
        "xGBuildup": "0"
    },
    {
        "goals": "0",
        "shots": "0",
        "xG": "0",
        "time": "90",
        "position": "GK",
        "h_team": "Middlesbrough",
        "a_team": "Arsenal",
        "h_goals": "1",
        "a_goals": "2",
        "date": "2017-04-17",
        "id": "3461",
        "season": "2016",
        "roster_id": "134704",
        "xA": "0",
        "assists": "0",
        "key_passes": "0",
        "npg": "0",
        "npxG": "0",
        "xGChain": "0",
        "xGBuildup": "0"
    },
    {
        "goals": "0",
        "shots": "0",
        "xG": "0",
        "time": "90",
        "position": "GK",
        "h_team": "Middlesbrough",
        "a_team": "Leicester",
        "h_goals": "0",
        "a_goals": "0",
        "date": "2017-01-02",
        "id": "3330",
        "season": "2016",
        "roster_id": "129531",
        "xA": "0",
        "assists": "0",
        "key_passes": "0",
        "npg": "0",
        "npxG": "0",
        "xGChain": "0",
        "xGBuildup": "0"
    },
    {
        "goals": "0",
        "shots": "0",
        "xG": "0",
        "time": "90",
        "position": "GK",
        "h_team": "West Bromwich Albion",
        "a_team": "Middlesbrough",
        "h_goals": "0",
        "a_goals": "0",
        "date": "2016-08-28",
        "id": "489",
        "season": "2016",
        "roster_id": "125954",
        "xA": "0",
        "assists": "0",
        "key_passes": "0",
        "npg": "0",
        "npxG": "0",
        "xGChain": "0.04855256900191307",
        "xGBuildup": "0.04855256900191307"
    },
    {
        "goals": "0",
        "shots": "0",
        "xG": "0",
        "time": "90",
        "position": "GK",
        "h_team": "Sunderland",
        "a_team": "Middlesbrough",
        "h_goals": "1",
        "a_goals": "2",
        "date": "2016-08-21",
        "id": "479",
        "season": "2016",
        "roster_id": "125537",
        "xA": "0",
        "assists": "0",
        "key_passes": "0",
        "npg": "0",
        "npxG": "0",
        "xGChain": "0.1349397599697113",
        "xGBuildup": "0.1349397599697113"
    },
    {
        "goals": "0",
        "shots": "0",
        "xG": "0",
        "time": "90",
        "position": "GK",
        "h_team": "Aston Villa",
        "a_team": "Southampton",
        "h_goals": "2",
        "a_goals": "4",
        "date": "2016-04-23",
        "id": "421",
        "season": "2015",
        "roster_id": "63079",
        "xA": "0",
        "assists": "0",
        "key_passes": "0",
        "npg": "0",
        "npxG": "0",
        "xGChain": "0",
        "xGBuildup": "0"
    },
    {
        "goals": "0",
        "shots": "0",
        "xG": "0",
        "time": "90",
        "position": "GK",
        "h_team": "Manchester United",
        "a_team": "Aston Villa",
        "h_goals": "1",
        "a_goals": "0",
        "date": "2016-04-16",
        "id": "406",
        "season": "2015",
        "roster_id": "62572",
        "xA": "0",
        "assists": "0",
        "key_passes": "0",
        "npg": "0",
        "npxG": "0",
        "xGChain": "0",
        "xGBuildup": "0"
    },
    {
        "goals": "0",
        "shots": "0",
        "xG": "0",
        "time": "90",
        "position": "GK",
        "h_team": "Aston Villa",
        "a_team": "Bournemouth",
        "h_goals": "1",
        "a_goals": "2",
        "date": "2016-04-09",
        "id": "398",
        "season": "2015",
        "roster_id": "66579",
        "xA": "0",
        "assists": "0",
        "key_passes": "0",
        "npg": "0",
        "npxG": "0",
        "xGChain": "0",
        "xGBuildup": "0"
    },
    {
        "goals": "0",
        "shots": "0",
        "xG": "0",
        "time": "90",
        "position": "GK",
        "h_team": "Aston Villa",
        "a_team": "Chelsea",
        "h_goals": "0",
        "a_goals": "4",
        "date": "2016-04-02",
        "id": "384",
        "season": "2015",
        "roster_id": "67299",
        "xA": "0",
        "assists": "0",
        "key_passes": "0",
        "npg": "0",
        "npxG": "0",
        "xGChain": "0.0319126732647419",
        "xGBuildup": "0.0319126732647419"
    },
    {
        "goals": "0",
        "shots": "0",
        "xG": "0",
        "time": "90",
        "position": "GK",
        "h_team": "Swansea",
        "a_team": "Aston Villa",
        "h_goals": "1",
        "a_goals": "0",
        "date": "2016-03-19",
        "id": "379",
        "season": "2015",
        "roster_id": "66760",
        "xA": "0",
        "assists": "0",
        "key_passes": "0",
        "npg": "0",
        "npxG": "0",
        "xGChain": "0",
        "xGBuildup": "0"
    },
    {
        "goals": "0",
        "shots": "0",
        "xG": "0",
        "time": "90",
        "position": "GK",
        "h_team": "Aston Villa",
        "a_team": "Tottenham",
        "h_goals": "0",
        "a_goals": "2",
        "date": "2016-03-13",
        "id": "372",
        "season": "2015",
        "roster_id": "66939",
        "xA": "0",
        "assists": "0",
        "key_passes": "0",
        "npg": "0",
        "npxG": "0",
        "xGChain": "0",
        "xGBuildup": "0"
    },
    {
        "goals": "0",
        "shots": "0",
        "xG": "0",
        "time": "90",
        "position": "GK",
        "h_team": "Manchester City",
        "a_team": "Aston Villa",
        "h_goals": "4",
        "a_goals": "0",
        "date": "2016-03-05",
        "id": "364",
        "season": "2015",
        "roster_id": "66071",
        "xA": "0",
        "assists": "0",
        "key_passes": "0",
        "npg": "0",
        "npxG": "0",
        "xGChain": "0",
        "xGBuildup": "0"
    },
    {
        "goals": "0",
        "shots": "0",
        "xG": "0",
        "time": "90",
        "position": "GK",
        "h_team": "Aston Villa",
        "a_team": "Everton",
        "h_goals": "1",
        "a_goals": "3",
        "date": "2016-03-01",
        "id": "349",
        "season": "2015",
        "roster_id": "66778",
        "xA": "0",
        "assists": "0",
        "key_passes": "0",
        "npg": "0",
        "npxG": "0",
        "xGChain": "0.08008891344070435",
        "xGBuildup": "0.08008891344070435"
    },
    {
        "goals": "0",
        "shots": "0",
        "xG": "0",
        "time": "90",
        "position": "GK",
        "h_team": "Sunderland",
        "a_team": "Aston Villa",
        "h_goals": "3",
        "a_goals": "1",
        "date": "2016-01-02",
        "id": "277",
        "season": "2015",
        "roster_id": "62047",
        "xA": "0",
        "assists": "0",
        "key_passes": "0",
        "npg": "0",
        "npxG": "0",
        "xGChain": "0.01784246414899826",
        "xGBuildup": "0.01784246414899826"
    },
    {
        "goals": "0",
        "shots": "0",
        "xG": "0",
        "time": "90",
        "position": "GK",
        "h_team": "Norwich",
        "a_team": "Aston Villa",
        "h_goals": "2",
        "a_goals": "0",
        "date": "2015-12-28",
        "id": "263",
        "season": "2015",
        "roster_id": "59381",
        "xA": "0",
        "assists": "0",
        "key_passes": "0",
        "npg": "0",
        "npxG": "0",
        "xGChain": "0",
        "xGBuildup": "0"
    },
    {
        "goals": "0",
        "shots": "0",
        "xG": "0",
        "time": "90",
        "position": "GK",
        "h_team": "Aston Villa",
        "a_team": "West Ham",
        "h_goals": "1",
        "a_goals": "1",
        "date": "2015-12-26",
        "id": "254",
        "season": "2015",
        "roster_id": "59450",
        "xA": "0",
        "assists": "0",
        "key_passes": "0",
        "npg": "0",
        "npxG": "0",
        "xGChain": "0.03468295559287071",
        "xGBuildup": "0.03468295559287071"
    },
    {
        "goals": "0",
        "shots": "0",
        "xG": "0",
        "time": "90",
        "position": "GK",
        "h_team": "Newcastle United",
        "a_team": "Aston Villa",
        "h_goals": "1",
        "a_goals": "1",
        "date": "2015-12-19",
        "id": "247",
        "season": "2015",
        "roster_id": "57952",
        "xA": "0",
        "assists": "0",
        "key_passes": "0",
        "npg": "0",
        "npxG": "0",
        "xGChain": "0",
        "xGBuildup": "0"
    },
    {
        "goals": "0",
        "shots": "0",
        "xG": "0",
        "time": "90",
        "position": "GK",
        "h_team": "Aston Villa",
        "a_team": "Arsenal",
        "h_goals": "0",
        "a_goals": "2",
        "date": "2015-12-13",
        "id": "237",
        "season": "2015",
        "roster_id": "58788",
        "xA": "0",
        "assists": "0",
        "key_passes": "0",
        "npg": "0",
        "npxG": "0",
        "xGChain": "0",
        "xGBuildup": "0"
    },
    {
        "goals": "0",
        "shots": "0",
        "xG": "0",
        "time": "90",
        "position": "GK",
        "h_team": "Southampton",
        "a_team": "Aston Villa",
        "h_goals": "1",
        "a_goals": "1",
        "date": "2015-12-05",
        "id": "227",
        "season": "2015",
        "roster_id": "60646",
        "xA": "0.04463285580277443",
        "assists": "0",
        "key_passes": "1",
        "npg": "0",
        "npxG": "0",
        "xGChain": "0.04463285580277443",
        "xGBuildup": "0"
    },
    {
        "goals": "0",
        "shots": "0",
        "xG": "0",
        "time": "90",
        "position": "GK",
        "h_team": "Aston Villa",
        "a_team": "Watford",
        "h_goals": "2",
        "a_goals": "3",
        "date": "2015-11-28",
        "id": "212",
        "season": "2015",
        "roster_id": "61617",
        "xA": "0",
        "assists": "0",
        "key_passes": "0",
        "npg": "0",
        "npxG": "0",
        "xGChain": "0",
        "xGBuildup": "0"
    },
    {
        "goals": "0",
        "shots": "0",
        "xG": "0",
        "time": "90",
        "position": "GK",
        "h_team": "Everton",
        "a_team": "Aston Villa",
        "h_goals": "4",
        "a_goals": "0",
        "date": "2015-11-21",
        "id": "206",
        "season": "2015",
        "roster_id": "59600",
        "xA": "0",
        "assists": "0",
        "key_passes": "0",
        "npg": "0",
        "npxG": "0",
        "xGChain": "0.022284256294369698",
        "xGBuildup": "0.022284256294369698"
    },
    {
        "goals": "0",
        "shots": "0",
        "xG": "0",
        "time": "90",
        "position": "GK",
        "h_team": "Aston Villa",
        "a_team": "Manchester City",
        "h_goals": "0",
        "a_goals": "0",
        "date": "2015-11-08",
        "id": "198",
        "season": "2015",
        "roster_id": "60108",
        "xA": "0",
        "assists": "0",
        "key_passes": "0",
        "npg": "0",
        "npxG": "0",
        "xGChain": "0",
        "xGBuildup": "0"
    },
    {
        "goals": "0",
        "shots": "0",
        "xG": "0",
        "time": "90",
        "position": "GK",
        "h_team": "Tottenham",
        "a_team": "Aston Villa",
        "h_goals": "3",
        "a_goals": "1",
        "date": "2015-11-03",
        "id": "190",
        "season": "2015",
        "roster_id": "59020",
        "xA": "0",
        "assists": "0",
        "key_passes": "0",
        "npg": "0",
        "npxG": "0",
        "xGChain": "0",
        "xGBuildup": "0"
    },
    {
        "goals": "0",
        "shots": "0",
        "xG": "0",
        "time": "90",
        "position": "GK",
        "h_team": "Aston Villa",
        "a_team": "Swansea",
        "h_goals": "1",
        "a_goals": "2",
        "date": "2015-10-24",
        "id": "171",
        "season": "2015",
        "roster_id": "65255",
        "xA": "0",
        "assists": "0",
        "key_passes": "0",
        "npg": "0",
        "npxG": "0",
        "xGChain": "0",
        "xGBuildup": "0"
    },
    {
        "goals": "0",
        "shots": "0",
        "xG": "0",
        "time": "90",
        "position": "GK",
        "h_team": "Chelsea",
        "a_team": "Aston Villa",
        "h_goals": "2",
        "a_goals": "0",
        "date": "2015-10-17",
        "id": "164",
        "season": "2015",
        "roster_id": "64941",
        "xA": "0",
        "assists": "0",
        "key_passes": "0",
        "npg": "0",
        "npxG": "0",
        "xGChain": "0.40232333540916443",
        "xGBuildup": "0.40232333540916443"
    },
    {
        "goals": "0",
        "shots": "0",
        "xG": "0",
        "time": "90",
        "position": "GK",
        "h_team": "Aston Villa",
        "a_team": "Stoke",
        "h_goals": "0",
        "a_goals": "1",
        "date": "2015-10-03",
        "id": "152",
        "season": "2015",
        "roster_id": "64680",
        "xA": "0",
        "assists": "0",
        "key_passes": "0",
        "npg": "0",
        "npxG": "0",
        "xGChain": "0.04210192710161209",
        "xGBuildup": "0.04210192710161209"
    },
    {
        "goals": "0",
        "shots": "0",
        "xG": "0",
        "time": "90",
        "position": "GK",
        "h_team": "Liverpool",
        "a_team": "Aston Villa",
        "h_goals": "3",
        "a_goals": "2",
        "date": "2015-09-26",
        "id": "145",
        "season": "2015",
        "roster_id": "64416",
        "xA": "0",
        "assists": "0",
        "key_passes": "0",
        "npg": "0",
        "npxG": "0",
        "xGChain": "0.046088337898254395",
        "xGBuildup": "0.046088337898254395"
    },
    {
        "goals": "0",
        "shots": "0",
        "xG": "0",
        "time": "90",
        "position": "GK",
        "h_team": "Aston Villa",
        "a_team": "West Bromwich Albion",
        "h_goals": "0",
        "a_goals": "1",
        "date": "2015-09-19",
        "id": "133",
        "season": "2015",
        "roster_id": "64098",
        "xA": "0",
        "assists": "0",
        "key_passes": "0",
        "npg": "0",
        "npxG": "0",
        "xGChain": "0",
        "xGBuildup": "0"
    },
    {
        "goals": "0",
        "shots": "0",
        "xG": "0",
        "time": "90",
        "position": "GK",
        "h_team": "Leicester",
        "a_team": "Aston Villa",
        "h_goals": "3",
        "a_goals": "2",
        "date": "2015-09-13",
        "id": "129",
        "season": "2015",
        "roster_id": "63917",
        "xA": "0",
        "assists": "0",
        "key_passes": "0",
        "npg": "0",
        "npxG": "0",
        "xGChain": "0",
        "xGBuildup": "0"
    },
    {
        "goals": "0",
        "shots": "0",
        "xG": "0",
        "time": "90",
        "position": "GK",
        "h_team": "Aston Villa",
        "a_team": "Sunderland",
        "h_goals": "2",
        "a_goals": "2",
        "date": "2015-08-29",
        "id": "113",
        "season": "2015",
        "roster_id": "63354",
        "xA": "0",
        "assists": "0",
        "key_passes": "0",
        "npg": "0",
        "npxG": "0",
        "xGChain": "0.6205440759658813",
        "xGBuildup": "0.6205440759658813"
    },
    {
        "goals": "0",
        "shots": "0",
        "xG": "0",
        "time": "90",
        "position": "GK",
        "h_team": "Crystal Palace",
        "a_team": "Aston Villa",
        "h_goals": "2",
        "a_goals": "1",
        "date": "2015-08-22",
        "id": "104",
        "season": "2015",
        "roster_id": "62491",
        "xA": "0",
        "assists": "0",
        "key_passes": "0",
        "npg": "0",
        "npxG": "0",
        "xGChain": "0.046710725873708725",
        "xGBuildup": "0.046710725873708725"
    },
    {
        "goals": "0",
        "shots": "0",
        "xG": "0",
        "time": "90",
        "position": "GK",
        "h_team": "Aston Villa",
        "a_team": "Manchester United",
        "h_goals": "0",
        "a_goals": "1",
        "date": "2015-08-14",
        "id": "91",
        "season": "2015",
        "roster_id": "57357",
        "xA": "0",
        "assists": "0",
        "key_passes": "0",
        "npg": "0",
        "npxG": "0",
        "xGChain": "0",
        "xGBuildup": "0"
    },
    {
        "goals": "0",
        "shots": "0",
        "xG": "0",
        "time": "90",
        "position": "GK",
        "h_team": "Bournemouth",
        "a_team": "Aston Villa",
        "h_goals": "0",
        "a_goals": "1",
        "date": "2015-08-08",
        "id": "82",
        "season": "2015",
        "roster_id": "548648",
        "xA": "0",
        "assists": "0",
        "key_passes": "0",
        "npg": "0",
        "npxG": "0",
        "xGChain": "0",
        "xGBuildup": "0"
    },
    {
        "goals": "0",
        "shots": "0",
        "xG": "0",
        "time": "90",
        "position": "GK",
        "h_team": "Manchester City",
        "a_team": "Aston Villa",
        "h_goals": "3",
        "a_goals": "2",
        "date": "2015-04-25",
        "id": "4475",
        "season": "2014",
        "roster_id": "25633",
        "xA": "0",
        "assists": "0",
        "key_passes": "0",
        "npg": "0",
        "npxG": "0",
        "xGChain": "0.012470569461584091",
        "xGBuildup": "0.012470569461584091"
    },
    {
        "goals": "0",
        "shots": "0",
        "xG": "0",
        "time": "90",
        "position": "GK",
        "h_team": "Tottenham",
        "a_team": "Aston Villa",
        "h_goals": "0",
        "a_goals": "1",
        "date": "2015-04-11",
        "id": "4455",
        "season": "2014",
        "roster_id": "24397",
        "xA": "0",
        "assists": "0",
        "key_passes": "0",
        "npg": "0",
        "npxG": "0",
        "xGChain": "0.01749921590089798",
        "xGBuildup": "0.01749921590089798"
    },
    {
        "goals": "0",
        "shots": "0",
        "xG": "0",
        "time": "90",
        "position": "GK",
        "h_team": "Aston Villa",
        "a_team": "Queens Park Rangers",
        "h_goals": "3",
        "a_goals": "3",
        "date": "2015-04-07",
        "id": "4450",
        "season": "2014",
        "roster_id": "25262",
        "xA": "0",
        "assists": "0",
        "key_passes": "0",
        "npg": "0",
        "npxG": "0",
        "xGChain": "0",
        "xGBuildup": "0"
    },
    {
        "goals": "0",
        "shots": "0",
        "xG": "0",
        "time": "90",
        "position": "GK",
        "h_team": "Manchester United",
        "a_team": "Aston Villa",
        "h_goals": "3",
        "a_goals": "1",
        "date": "2015-04-04",
        "id": "4443",
        "season": "2014",
        "roster_id": "25083",
        "xA": "0",
        "assists": "0",
        "key_passes": "0",
        "npg": "0",
        "npxG": "0",
        "xGChain": "0.10995620489120483",
        "xGBuildup": "0.10995620489120483"
    },
    {
        "goals": "0",
        "shots": "0",
        "xG": "0",
        "time": "90",
        "position": "GK",
        "h_team": "Aston Villa",
        "a_team": "Swansea",
        "h_goals": "0",
        "a_goals": "1",
        "date": "2015-03-21",
        "id": "4504",
        "season": "2014",
        "roster_id": "24135",
        "xA": "0",
        "assists": "0",
        "key_passes": "0",
        "npg": "0",
        "npxG": "0",
        "xGChain": "0.03087605908513069",
        "xGBuildup": "0.03087605908513069"
    },
    {
        "goals": "0",
        "shots": "0",
        "xG": "0",
        "time": "90",
        "position": "GK",
        "h_team": "Sunderland",
        "a_team": "Aston Villa",
        "h_goals": "0",
        "a_goals": "4",
        "date": "2015-03-14",
        "id": "4497",
        "season": "2014",
        "roster_id": "23488",
        "xA": "0",
        "assists": "0",
        "key_passes": "0",
        "npg": "0",
        "npxG": "0",
        "xGChain": "0.1050843894481659",
        "xGBuildup": "0.1050843894481659"
    },
    {
        "goals": "0",
        "shots": "0",
        "xG": "0",
        "time": "90",
        "position": "GK",
        "h_team": "Aston Villa",
        "a_team": "West Bromwich Albion",
        "h_goals": "2",
        "a_goals": "1",
        "date": "2015-03-03",
        "id": "4482",
        "season": "2014",
        "roster_id": "27124",
        "xA": "0",
        "assists": "0",
        "key_passes": "0",
        "npg": "0",
        "npxG": "0",
        "xGChain": "0.09114909917116165",
        "xGBuildup": "0.09114909917116165"
    },
    {
        "goals": "0",
        "shots": "0",
        "xG": "0",
        "time": "90",
        "position": "GK",
        "h_team": "Newcastle United",
        "a_team": "Aston Villa",
        "h_goals": "1",
        "a_goals": "0",
        "date": "2015-02-28",
        "id": "4548",
        "season": "2014",
        "roster_id": "26591",
        "xA": "0",
        "assists": "0",
        "key_passes": "0",
        "npg": "0",
        "npxG": "0",
        "xGChain": "0.03930281102657318",
        "xGBuildup": "0.03930281102657318"
    },
    {
        "goals": "0",
        "shots": "0",
        "xG": "0",
        "time": "90",
        "position": "GK",
        "h_team": "Aston Villa",
        "a_team": "Stoke",
        "h_goals": "1",
        "a_goals": "2",
        "date": "2015-02-21",
        "id": "4535",
        "season": "2014",
        "roster_id": "26632",
        "xA": "0",
        "assists": "0",
        "key_passes": "0",
        "npg": "0",
        "npxG": "0",
        "xGChain": "0",
        "xGBuildup": "0"
    },
    {
        "goals": "0",
        "shots": "0",
        "xG": "0",
        "time": "90",
        "position": "GK",
        "h_team": "Hull",
        "a_team": "Aston Villa",
        "h_goals": "2",
        "a_goals": "0",
        "date": "2015-02-10",
        "id": "4527",
        "season": "2014",
        "roster_id": "27002",
        "xA": "0",
        "assists": "0",
        "key_passes": "0",
        "npg": "0",
        "npxG": "0",
        "xGChain": "0",
        "xGBuildup": "0"
    },
    {
        "goals": "0",
        "shots": "0",
        "xG": "0",
        "time": "90",
        "position": "GK",
        "h_team": "Aston Villa",
        "a_team": "Chelsea",
        "h_goals": "1",
        "a_goals": "2",
        "date": "2015-02-07",
        "id": "4516",
        "season": "2014",
        "roster_id": "27041",
        "xA": "0",
        "assists": "0",
        "key_passes": "0",
        "npg": "0",
        "npxG": "0",
        "xGChain": "0",
        "xGBuildup": "0"
    },
    {
        "goals": "0",
        "shots": "0",
        "xG": "0",
        "time": "90",
        "position": "GK",
        "h_team": "Arsenal",
        "a_team": "Aston Villa",
        "h_goals": "5",
        "a_goals": "0",
        "date": "2015-02-01",
        "id": "4513",
        "season": "2014",
        "roster_id": "22363",
        "xA": "0",
        "assists": "0",
        "key_passes": "0",
        "npg": "0",
        "npxG": "0",
        "xGChain": "0",
        "xGBuildup": "0"
    },
    {
        "goals": "0",
        "shots": "0",
        "xG": "0",
        "time": "90",
        "position": "GK",
        "h_team": "Aston Villa",
        "a_team": "Liverpool",
        "h_goals": "0",
        "a_goals": "2",
        "date": "2015-01-17",
        "id": "4571",
        "season": "2014",
        "roster_id": "21264",
        "xA": "0",
        "assists": "0",
        "key_passes": "0",
        "npg": "0",
        "npxG": "0",
        "xGChain": "0",
        "xGBuildup": "0"
    },
    {
        "goals": "0",
        "shots": "0",
        "xG": "0",
        "time": "90",
        "position": "GK",
        "h_team": "Leicester",
        "a_team": "Aston Villa",
        "h_goals": "1",
        "a_goals": "0",
        "date": "2015-01-10",
        "id": "4567",
        "season": "2014",
        "roster_id": "20730",
        "xA": "0",
        "assists": "0",
        "key_passes": "0",
        "npg": "0",
        "npxG": "0",
        "xGChain": "0",
        "xGBuildup": "0"
    },
    {
        "goals": "0",
        "shots": "0",
        "xG": "0",
        "time": "90",
        "position": "GK",
        "h_team": "Aston Villa",
        "a_team": "Crystal Palace",
        "h_goals": "0",
        "a_goals": "0",
        "date": "2015-01-01",
        "id": "4557",
        "season": "2014",
        "roster_id": "22211",
        "xA": "0",
        "assists": "0",
        "key_passes": "0",
        "npg": "0",
        "npxG": "0",
        "xGChain": "0",
        "xGBuildup": "0"
    },
    {
        "goals": "0",
        "shots": "0",
        "xG": "0",
        "time": "90",
        "position": "GK",
        "h_team": "Aston Villa",
        "a_team": "Sunderland",
        "h_goals": "0",
        "a_goals": "0",
        "date": "2014-12-28",
        "id": "4644",
        "season": "2014",
        "roster_id": "21129",
        "xA": "0",
        "assists": "0",
        "key_passes": "0",
        "npg": "0",
        "npxG": "0",
        "xGChain": "0.05045224353671074",
        "xGBuildup": "0.05045224353671074"
    },
    {
        "goals": "0",
        "shots": "0",
        "xG": "0",
        "time": "90",
        "position": "GK",
        "h_team": "Swansea",
        "a_team": "Aston Villa",
        "h_goals": "1",
        "a_goals": "0",
        "date": "2014-12-26",
        "id": "4631",
        "season": "2014",
        "roster_id": "20923",
        "xA": "0",
        "assists": "0",
        "key_passes": "0",
        "npg": "0",
        "npxG": "0",
        "xGChain": "0",
        "xGBuildup": "0"
    },
    {
        "goals": "0",
        "shots": "0",
        "xG": "0",
        "time": "90",
        "position": "GK",
        "h_team": "Aston Villa",
        "a_team": "Manchester United",
        "h_goals": "1",
        "a_goals": "1",
        "date": "2014-12-20",
        "id": "4624",
        "season": "2014",
        "roster_id": "21507",
        "xA": "0",
        "assists": "0",
        "key_passes": "0",
        "npg": "0",
        "npxG": "0",
        "xGChain": "0.017262300476431847",
        "xGBuildup": "0.017262300476431847"
    },
    {
        "goals": "0",
        "shots": "0",
        "xG": "0",
        "time": "90",
        "position": "GK",
        "h_team": "West Bromwich Albion",
        "a_team": "Aston Villa",
        "h_goals": "1",
        "a_goals": "0",
        "date": "2014-12-13",
        "id": "4612",
        "season": "2014",
        "roster_id": "21414",
        "xA": "0",
        "assists": "0",
        "key_passes": "0",
        "npg": "0",
        "npxG": "0",
        "xGChain": "0.05133314058184624",
        "xGBuildup": "0.05133314058184624"
    },
    {
        "goals": "0",
        "shots": "0",
        "xG": "0",
        "time": "90",
        "position": "GK",
        "h_team": "Aston Villa",
        "a_team": "Leicester",
        "h_goals": "2",
        "a_goals": "1",
        "date": "2014-12-07",
        "id": "4607",
        "season": "2014",
        "roster_id": "22709",
        "xA": "0",
        "assists": "0",
        "key_passes": "0",
        "npg": "0",
        "npxG": "0",
        "xGChain": "0.16341879963874817",
        "xGBuildup": "0.16341879963874817"
    },
    {
        "goals": "0",
        "shots": "0",
        "xG": "0",
        "time": "90",
        "position": "GK",
        "h_team": "Crystal Palace",
        "a_team": "Aston Villa",
        "h_goals": "0",
        "a_goals": "1",
        "date": "2014-12-02",
        "id": "4593",
        "season": "2014",
        "roster_id": "22198",
        "xA": "0",
        "assists": "0",
        "key_passes": "0",
        "npg": "0",
        "npxG": "0",
        "xGChain": "0",
        "xGBuildup": "0"
    },
    {
        "goals": "0",
        "shots": "0",
        "xG": "0",
        "time": "90",
        "position": "GK",
        "h_team": "Burnley",
        "a_team": "Aston Villa",
        "h_goals": "1",
        "a_goals": "1",
        "date": "2014-11-29",
        "id": "4685",
        "season": "2014",
        "roster_id": "20077",
        "xA": "0",
        "assists": "0",
        "key_passes": "0",
        "npg": "0",
        "npxG": "0",
        "xGChain": "0.01702704466879368",
        "xGBuildup": "0.01702704466879368"
    },
    {
        "goals": "0",
        "shots": "0",
        "xG": "0",
        "time": "90",
        "position": "GK",
        "h_team": "Aston Villa",
        "a_team": "Southampton",
        "h_goals": "1",
        "a_goals": "1",
        "date": "2014-11-24",
        "id": "4678",
        "season": "2014",
        "roster_id": "18905",
        "xA": "0",
        "assists": "0",
        "key_passes": "0",
        "npg": "0",
        "npxG": "0",
        "xGChain": "0",
        "xGBuildup": "0"
    },
    {
        "goals": "0",
        "shots": "0",
        "xG": "0",
        "time": "90",
        "position": "GK",
        "h_team": "West Ham",
        "a_team": "Aston Villa",
        "h_goals": "0",
        "a_goals": "0",
        "date": "2014-11-08",
        "id": "4662",
        "season": "2014",
        "roster_id": "18727",
        "xA": "0",
        "assists": "0",
        "key_passes": "0",
        "npg": "0",
        "npxG": "0",
        "xGChain": "0",
        "xGBuildup": "0"
    },
    {
        "goals": "0",
        "shots": "0",
        "xG": "0",
        "time": "90",
        "position": "GK",
        "h_team": "Aston Villa",
        "a_team": "Tottenham",
        "h_goals": "1",
        "a_goals": "2",
        "date": "2014-11-02",
        "id": "4657",
        "season": "2014",
        "roster_id": "19594",
        "xA": "0",
        "assists": "0",
        "key_passes": "0",
        "npg": "0",
        "npxG": "0",
        "xGChain": "0.24199563264846802",
        "xGBuildup": "0.24199563264846802"
    },
    {
        "goals": "0",
        "shots": "0",
        "xG": "0",
        "time": "90",
        "position": "GK",
        "h_team": "Queens Park Rangers",
        "a_team": "Aston Villa",
        "h_goals": "2",
        "a_goals": "0",
        "date": "2014-10-27",
        "id": "4718",
        "season": "2014",
        "roster_id": "20378",
        "xA": "0",
        "assists": "0",
        "key_passes": "0",
        "npg": "0",
        "npxG": "0",
        "xGChain": "0",
        "xGBuildup": "0"
    },
    {
        "goals": "0",
        "shots": "0",
        "xG": "0",
        "time": "90",
        "position": "GK",
        "h_team": "Everton",
        "a_team": "Aston Villa",
        "h_goals": "3",
        "a_goals": "0",
        "date": "2014-10-18",
        "id": "4700",
        "season": "2014",
        "roster_id": "19055",
        "xA": "0",
        "assists": "0",
        "key_passes": "0",
        "npg": "0",
        "npxG": "0",
        "xGChain": "0.01406185980886221",
        "xGBuildup": "0.01406185980886221"
    },
    {
        "goals": "0",
        "shots": "0",
        "xG": "0",
        "time": "90",
        "position": "GK",
        "h_team": "Aston Villa",
        "a_team": "Manchester City",
        "h_goals": "0",
        "a_goals": "2",
        "date": "2014-10-04",
        "id": "4694",
        "season": "2014",
        "roster_id": "19290",
        "xA": "0",
        "assists": "0",
        "key_passes": "0",
        "npg": "0",
        "npxG": "0",
        "xGChain": "0",
        "xGBuildup": "0"
    },
    {
        "goals": "0",
        "shots": "0",
        "xG": "0",
        "time": "90",
        "position": "GK",
        "h_team": "Chelsea",
        "a_team": "Aston Villa",
        "h_goals": "3",
        "a_goals": "0",
        "date": "2014-09-27",
        "id": "4742",
        "season": "2014",
        "roster_id": "18450",
        "xA": "0",
        "assists": "0",
        "key_passes": "0",
        "npg": "0",
        "npxG": "0",
        "xGChain": "0",
        "xGBuildup": "0"
    },
    {
        "goals": "0",
        "shots": "0",
        "xG": "0",
        "time": "90",
        "position": "GK",
        "h_team": "Aston Villa",
        "a_team": "Arsenal",
        "h_goals": "0",
        "a_goals": "3",
        "date": "2014-09-20",
        "id": "4731",
        "season": "2014",
        "roster_id": "18132",
        "xA": "0",
        "assists": "0",
        "key_passes": "0",
        "npg": "0",
        "npxG": "0",
        "xGChain": "0",
        "xGBuildup": "0"
    },
    {
        "goals": "0",
        "shots": "0",
        "xG": "0",
        "time": "90",
        "position": "GK",
        "h_team": "Liverpool",
        "a_team": "Aston Villa",
        "h_goals": "0",
        "a_goals": "1",
        "date": "2014-09-13",
        "id": "4726",
        "season": "2014",
        "roster_id": "17979",
        "xA": "0",
        "assists": "0",
        "key_passes": "0",
        "npg": "0",
        "npxG": "0",
        "xGChain": "0",
        "xGBuildup": "0"
    },
    {
        "goals": "0",
        "shots": "0",
        "xG": "0",
        "time": "90",
        "position": "GK",
        "h_team": "Aston Villa",
        "a_team": "Hull",
        "h_goals": "2",
        "a_goals": "1",
        "date": "2014-08-31",
        "id": "4776",
        "season": "2014",
        "roster_id": "17578",
        "xA": "0",
        "assists": "0",
        "key_passes": "0",
        "npg": "0",
        "npxG": "0",
        "xGChain": "0.04011538252234459",
        "xGBuildup": "0.04011538252234459"
    },
    {
        "goals": "0",
        "shots": "0",
        "xG": "0",
        "time": "90",
        "position": "GK",
        "h_team": "Aston Villa",
        "a_team": "Newcastle United",
        "h_goals": "0",
        "a_goals": "0",
        "date": "2014-08-23",
        "id": "4759",
        "season": "2014",
        "roster_id": "17299",
        "xA": "0",
        "assists": "0",
        "key_passes": "0",
        "npg": "0",
        "npxG": "0",
        "xGChain": "0",
        "xGBuildup": "0"
    },
    {
        "goals": "0",
        "shots": "0",
        "xG": "0",
        "time": "90",
        "position": "GK",
        "h_team": "Stoke",
        "a_team": "Aston Villa",
        "h_goals": "0",
        "a_goals": "1",
        "date": "2014-08-16",
        "id": "4752",
        "season": "2014",
        "roster_id": "17230",
        "xA": "0",
        "assists": "0",
        "key_passes": "0",
        "npg": "0",
        "npxG": "0",
        "xGChain": "0.10871196538209915",
        "xGBuildup": "0.10871196538209915"
    }
]