[
    {
        "goals": "0",
        "shots": "0",
        "xG": "0",
        "time": "90",
        "position": "GK",
        "h_team": "Bournemouth",
        "a_team": "Leicester",
        "h_goals": "2",
        "a_goals": "1",
        "date": "2022-10-08",
        "id": "18293",
        "season": "2022",
        "roster_id": "554057",
        "xA": "0",
        "assists": "0",
        "key_passes": "0",
        "npg": "0",
        "npxG": "0",
        "xGChain": "0.08019236475229263",
        "xGBuildup": "0.08019236475229263"
    },
    {
        "goals": "0",
        "shots": "0",
        "xG": "0",
        "time": "90",
        "position": "GK",
        "h_team": "Bournemouth",
        "a_team": "Brentford",
        "h_goals": "0",
        "a_goals": "0",
        "date": "2022-10-01",
        "id": "18283",
        "season": "2022",
        "roster_id": "552391",
        "xA": "0",
        "assists": "0",
        "key_passes": "0",
        "npg": "0",
        "npxG": "0",
        "xGChain": "0.09898138046264648",
        "xGBuildup": "0.09898138046264648"
    },
    {
        "goals": "0",
        "shots": "0",
        "xG": "0",
        "time": "90",
        "position": "GK",
        "h_team": "Newcastle United",
        "a_team": "Bournemouth",
        "h_goals": "1",
        "a_goals": "1",
        "date": "2022-09-17",
        "id": "18275",
        "season": "2022",
        "roster_id": "550688",
        "xA": "0",
        "assists": "0",
        "key_passes": "0",
        "npg": "0",
        "npxG": "0",
        "xGChain": "0",
        "xGBuildup": "0"
    },
    {
        "goals": "0",
        "shots": "0",
        "xG": "0",
        "time": "90",
        "position": "GK",
        "h_team": "Nottingham Forest",
        "a_team": "Bournemouth",
        "h_goals": "2",
        "a_goals": "3",
        "date": "2022-09-03",
        "id": "18254",
        "season": "2022",
        "roster_id": "547139",
        "xA": "0",
        "assists": "0",
        "key_passes": "0",
        "npg": "0",
        "npxG": "0",
        "xGChain": "0",
        "xGBuildup": "0"
    },
    {
        "goals": "0",
        "shots": "0",
        "xG": "0",
        "time": "90",
        "position": "GK",
        "h_team": "Bournemouth",
        "a_team": "Wolverhampton Wanderers",
        "h_goals": "0",
        "a_goals": "0",
        "date": "2022-08-31",
        "id": "18248",
        "season": "2022",
        "roster_id": "546282",
        "xA": "0",
        "assists": "0",
        "key_passes": "0",
        "npg": "0",
        "npxG": "0",
        "xGChain": "0.013050537556409836",
        "xGBuildup": "0.013050537556409836"
    },
    {
        "goals": "0",
        "shots": "0",
        "xG": "0",
        "time": "90",
        "position": "GK",
        "h_team": "Real Betis",
        "a_team": "Barcelona",
        "h_goals": "1",
        "a_goals": "2",
        "date": "2022-05-07",
        "id": "17478",
        "season": "2021",
        "roster_id": "533162",
        "xA": "0.03827076777815819",
        "assists": "0",
        "key_passes": "1",
        "npg": "0",
        "npxG": "0",
        "xGChain": "0.03827076777815819",
        "xGBuildup": "0"
    },
    {
        "goals": "0",
        "shots": "0",
        "xG": "0",
        "time": "90",
        "position": "GK",
        "h_team": "Athletic Club",
        "a_team": "Barcelona",
        "h_goals": "1",
        "a_goals": "1",
        "date": "2021-08-21",
        "id": "17150",
        "season": "2021",
        "roster_id": "477456",
        "xA": "0",
        "assists": "0",
        "key_passes": "0",
        "npg": "0",
        "npxG": "0",
        "xGChain": "0.08972620218992233",
        "xGBuildup": "0.08972620218992233"
    },
    {
        "goals": "0",
        "shots": "0",
        "xG": "0",
        "time": "90",
        "position": "GK",
        "h_team": "Barcelona",
        "a_team": "Real Sociedad",
        "h_goals": "4",
        "a_goals": "2",
        "date": "2021-08-15",
        "id": "17142",
        "season": "2021",
        "roster_id": "476381",
        "xA": "0",
        "assists": "0",
        "key_passes": "0",
        "npg": "0",
        "npxG": "0",
        "xGChain": "0.35336145758628845",
        "xGBuildup": "0.35336145758628845"
    },
    {
        "goals": "0",
        "shots": "0",
        "xG": "0",
        "time": "90",
        "position": "GK",
        "h_team": "Eibar",
        "a_team": "Barcelona",
        "h_goals": "0",
        "a_goals": "1",
        "date": "2021-05-22",
        "id": "15149",
        "season": "2020",
        "roster_id": "472957",
        "xA": "0",
        "assists": "0",
        "key_passes": "0",
        "npg": "0",
        "npxG": "0",
        "xGChain": "0.07804232090711594",
        "xGBuildup": "0.07804232090711594"
    },
    {
        "goals": "0",
        "shots": "0",
        "xG": "0",
        "time": "90",
        "position": "GK",
        "h_team": "Alaves",
        "a_team": "Barcelona",
        "h_goals": "1",
        "a_goals": "1",
        "date": "2020-10-31",
        "id": "14845",
        "season": "2020",
        "roster_id": "424775",
        "xA": "0",
        "assists": "0",
        "key_passes": "0",
        "npg": "0",
        "npxG": "0",
        "xGChain": "0.45743703842163086",
        "xGBuildup": "0.45743703842163086"
    },
    {
        "goals": "0",
        "shots": "0",
        "xG": "0",
        "time": "90",
        "position": "GK",
        "h_team": "Barcelona",
        "a_team": "Real Madrid",
        "h_goals": "1",
        "a_goals": "3",
        "date": "2020-10-24",
        "id": "14836",
        "season": "2020",
        "roster_id": "422820",
        "xA": "0",
        "assists": "0",
        "key_passes": "0",
        "npg": "0",
        "npxG": "0",
        "xGChain": "0.395498126745224",
        "xGBuildup": "0.395498126745224"
    },
    {
        "goals": "0",
        "shots": "0",
        "xG": "0",
        "time": "90",
        "position": "GK",
        "h_team": "Getafe",
        "a_team": "Barcelona",
        "h_goals": "1",
        "a_goals": "0",
        "date": "2020-10-17",
        "id": "14830",
        "season": "2020",
        "roster_id": "421494",
        "xA": "0",
        "assists": "0",
        "key_passes": "0",
        "npg": "0",
        "npxG": "0",
        "xGChain": "0",
        "xGBuildup": "0"
    },
    {
        "goals": "0",
        "shots": "0",
        "xG": "0",
        "time": "90",
        "position": "GK",
        "h_team": "Barcelona",
        "a_team": "Sevilla",
        "h_goals": "1",
        "a_goals": "1",
        "date": "2020-10-04",
        "id": "14817",
        "season": "2020",
        "roster_id": "420662",
        "xA": "0",
        "assists": "0",
        "key_passes": "0",
        "npg": "0",
        "npxG": "0",
        "xGChain": "0.245496928691864",
        "xGBuildup": "0.245496928691864"
    },
    {
        "goals": "0",
        "shots": "0",
        "xG": "0",
        "time": "90",
        "position": "GK",
        "h_team": "Celta Vigo",
        "a_team": "Barcelona",
        "h_goals": "0",
        "a_goals": "3",
        "date": "2020-10-01",
        "id": "14165",
        "season": "2020",
        "roster_id": "419083",
        "xA": "0",
        "assists": "0",
        "key_passes": "0",
        "npg": "0",
        "npxG": "0",
        "xGChain": "0.08138638734817505",
        "xGBuildup": "0.08138638734817505"
    },
    {
        "goals": "0",
        "shots": "0",
        "xG": "0",
        "time": "90",
        "position": "GK",
        "h_team": "Barcelona",
        "a_team": "Villarreal",
        "h_goals": "4",
        "a_goals": "0",
        "date": "2020-09-27",
        "id": "14156",
        "season": "2020",
        "roster_id": "418509",
        "xA": "0",
        "assists": "0",
        "key_passes": "0",
        "npg": "0",
        "npxG": "0",
        "xGChain": "1.0247962474822998",
        "xGBuildup": "1.0247962474822998"
    },
    {
        "goals": "0",
        "shots": "0",
        "xG": "0",
        "time": "90",
        "position": "GK",
        "h_team": "Alaves",
        "a_team": "Barcelona",
        "h_goals": "0",
        "a_goals": "5",
        "date": "2020-07-19",
        "id": "12393",
        "season": "2019",
        "roster_id": "409830",
        "xA": "0",
        "assists": "0",
        "key_passes": "0",
        "npg": "0",
        "npxG": "0",
        "xGChain": "0.343767911195755",
        "xGBuildup": "0.343767911195755"
    },
    {
        "goals": "0",
        "shots": "0",
        "xG": "0",
        "time": "90",
        "position": "GK",
        "h_team": "Espanyol",
        "a_team": "Barcelona",
        "h_goals": "2",
        "a_goals": "2",
        "date": "2020-01-04",
        "id": "12206",
        "season": "2019",
        "roster_id": "388042",
        "xA": "0",
        "assists": "0",
        "key_passes": "0",
        "npg": "0",
        "npxG": "0",
        "xGChain": "0.4359090328216553",
        "xGBuildup": "0.4359090328216553"
    },
    {
        "goals": "0",
        "shots": "0",
        "xG": "0",
        "time": "90",
        "position": "GK",
        "h_team": "SD Huesca",
        "a_team": "Valencia",
        "h_goals": "2",
        "a_goals": "6",
        "date": "2019-05-05",
        "id": "10314",
        "season": "2018",
        "roster_id": "331271",
        "xA": "0",
        "assists": "0",
        "key_passes": "0",
        "npg": "0",
        "npxG": "0",
        "xGChain": "0.7412689924240112",
        "xGBuildup": "0.7412689924240112"
    },
    {
        "goals": "0",
        "shots": "0",
        "xG": "0",
        "time": "90",
        "position": "GK",
        "h_team": "Valencia",
        "a_team": "Eibar",
        "h_goals": "0",
        "a_goals": "1",
        "date": "2019-04-28",
        "id": "10299",
        "season": "2018",
        "roster_id": "328601",
        "xA": "0",
        "assists": "0",
        "key_passes": "0",
        "npg": "0",
        "npxG": "0",
        "xGChain": "0",
        "xGBuildup": "0"
    },
    {
        "goals": "0",
        "shots": "0",
        "xG": "0",
        "time": "90",
        "position": "GK",
        "h_team": "Atletico Madrid",
        "a_team": "Valencia",
        "h_goals": "3",
        "a_goals": "2",
        "date": "2019-04-24",
        "id": "10295",
        "season": "2018",
        "roster_id": "327509",
        "xA": "0",
        "assists": "0",
        "key_passes": "0",
        "npg": "0",
        "npxG": "0",
        "xGChain": "0",
        "xGBuildup": "0"
    },
    {
        "goals": "0",
        "shots": "0",
        "xG": "0",
        "time": "90",
        "position": "GK",
        "h_team": "Real Betis",
        "a_team": "Valencia",
        "h_goals": "1",
        "a_goals": "2",
        "date": "2019-04-21",
        "id": "10284",
        "season": "2018",
        "roster_id": "326905",
        "xA": "0",
        "assists": "0",
        "key_passes": "0",
        "npg": "0",
        "npxG": "0",
        "xGChain": "0",
        "xGBuildup": "0"
    },
    {
        "goals": "0",
        "shots": "0",
        "xG": "0",
        "time": "90",
        "position": "GK",
        "h_team": "Valencia",
        "a_team": "Levante",
        "h_goals": "3",
        "a_goals": "1",
        "date": "2019-04-14",
        "id": "10272",
        "season": "2018",
        "roster_id": "325203",
        "xA": "0",
        "assists": "0",
        "key_passes": "0",
        "npg": "0",
        "npxG": "0",
        "xGChain": "0",
        "xGBuildup": "0"
    },
    {
        "goals": "0",
        "shots": "0",
        "xG": "0",
        "time": "90",
        "position": "GK",
        "h_team": "Rayo Vallecano",
        "a_team": "Valencia",
        "h_goals": "2",
        "a_goals": "0",
        "date": "2019-04-06",
        "id": "10265",
        "season": "2018",
        "roster_id": "322777",
        "xA": "0",
        "assists": "0",
        "key_passes": "0",
        "npg": "0",
        "npxG": "0",
        "xGChain": "0",
        "xGBuildup": "0"
    },
    {
        "goals": "0",
        "shots": "0",
        "xG": "0",
        "time": "90",
        "position": "GK",
        "h_team": "Valencia",
        "a_team": "Real Madrid",
        "h_goals": "2",
        "a_goals": "1",
        "date": "2019-04-03",
        "id": "10256",
        "season": "2018",
        "roster_id": "322099",
        "xA": "0",
        "assists": "0",
        "key_passes": "0",
        "npg": "0",
        "npxG": "0",
        "xGChain": "0.25710996985435486",
        "xGBuildup": "0.25710996985435486"
    },
    {
        "goals": "0",
        "shots": "0",
        "xG": "0",
        "time": "90",
        "position": "GK",
        "h_team": "Sevilla",
        "a_team": "Valencia",
        "h_goals": "0",
        "a_goals": "1",
        "date": "2019-03-31",
        "id": "10238",
        "season": "2018",
        "roster_id": "318594",
        "xA": "0",
        "assists": "0",
        "key_passes": "0",
        "npg": "0",
        "npxG": "0",
        "xGChain": "0",
        "xGBuildup": "0"
    },
    {
        "goals": "0",
        "shots": "0",
        "xG": "0",
        "time": "90",
        "position": "GK",
        "h_team": "Girona",
        "a_team": "Valencia",
        "h_goals": "2",
        "a_goals": "3",
        "date": "2019-03-10",
        "id": "10221",
        "season": "2018",
        "roster_id": "315274",
        "xA": "0",
        "assists": "0",
        "key_passes": "0",
        "npg": "0",
        "npxG": "0",
        "xGChain": "0",
        "xGBuildup": "0"
    },
    {
        "goals": "0",
        "shots": "0",
        "xG": "0",
        "time": "90",
        "position": "GK",
        "h_team": "Valencia",
        "a_team": "Athletic Club",
        "h_goals": "2",
        "a_goals": "0",
        "date": "2019-03-03",
        "id": "10210",
        "season": "2018",
        "roster_id": "311633",
        "xA": "0.03703302890062332",
        "assists": "0",
        "key_passes": "1",
        "npg": "0",
        "npxG": "0",
        "xGChain": "0.03703302890062332",
        "xGBuildup": "0"
    },
    {
        "goals": "0",
        "shots": "0",
        "xG": "0",
        "time": "90",
        "position": "GK",
        "h_team": "Leganes",
        "a_team": "Valencia",
        "h_goals": "1",
        "a_goals": "1",
        "date": "2019-02-24",
        "id": "10200",
        "season": "2018",
        "roster_id": "311255",
        "xA": "0",
        "assists": "0",
        "key_passes": "0",
        "npg": "0",
        "npxG": "0",
        "xGChain": "0",
        "xGBuildup": "0"
    },
    {
        "goals": "0",
        "shots": "0",
        "xG": "0",
        "time": "90",
        "position": "GK",
        "h_team": "Valencia",
        "a_team": "Espanyol",
        "h_goals": "0",
        "a_goals": "0",
        "date": "2019-02-17",
        "id": "10190",
        "season": "2018",
        "roster_id": "310989",
        "xA": "0",
        "assists": "0",
        "key_passes": "0",
        "npg": "0",
        "npxG": "0",
        "xGChain": "0.04117804393172264",
        "xGBuildup": "0.04117804393172264"
    },
    {
        "goals": "0",
        "shots": "0",
        "xG": "0",
        "time": "90",
        "position": "GK",
        "h_team": "Valencia",
        "a_team": "Real Sociedad",
        "h_goals": "0",
        "a_goals": "0",
        "date": "2019-02-10",
        "id": "10186",
        "season": "2018",
        "roster_id": "310682",
        "xA": "0",
        "assists": "0",
        "key_passes": "0",
        "npg": "0",
        "npxG": "0",
        "xGChain": "0.021725546568632126",
        "xGBuildup": "0.021725546568632126"
    },
    {
        "goals": "0",
        "shots": "0",
        "xG": "0",
        "time": "90",
        "position": "GK",
        "h_team": "Barcelona",
        "a_team": "Valencia",
        "h_goals": "2",
        "a_goals": "2",
        "date": "2019-02-02",
        "id": "10167",
        "season": "2018",
        "roster_id": "310306",
        "xA": "0",
        "assists": "0",
        "key_passes": "0",
        "npg": "0",
        "npxG": "0",
        "xGChain": "0",
        "xGBuildup": "0"
    },
    {
        "goals": "0",
        "shots": "0",
        "xG": "0",
        "time": "90",
        "position": "GK",
        "h_team": "Valencia",
        "a_team": "Villarreal",
        "h_goals": "3",
        "a_goals": "0",
        "date": "2019-01-26",
        "id": "10162",
        "season": "2018",
        "roster_id": "309901",
        "xA": "0",
        "assists": "0",
        "key_passes": "0",
        "npg": "0",
        "npxG": "0",
        "xGChain": "0",
        "xGBuildup": "0"
    },
    {
        "goals": "0",
        "shots": "0",
        "xG": "0",
        "time": "90",
        "position": "GK",
        "h_team": "Celta Vigo",
        "a_team": "Valencia",
        "h_goals": "1",
        "a_goals": "2",
        "date": "2019-01-19",
        "id": "10154",
        "season": "2018",
        "roster_id": "309720",
        "xA": "0",
        "assists": "0",
        "key_passes": "0",
        "npg": "0",
        "npxG": "0",
        "xGChain": "0",
        "xGBuildup": "0"
    },
    {
        "goals": "0",
        "shots": "0",
        "xG": "0",
        "time": "90",
        "position": "GK",
        "h_team": "Valencia",
        "a_team": "Real Valladolid",
        "h_goals": "1",
        "a_goals": "1",
        "date": "2019-01-12",
        "id": "10142",
        "season": "2018",
        "roster_id": "309400",
        "xA": "0",
        "assists": "0",
        "key_passes": "0",
        "npg": "0",
        "npxG": "0",
        "xGChain": "0",
        "xGBuildup": "0"
    },
    {
        "goals": "0",
        "shots": "0",
        "xG": "0",
        "time": "90",
        "position": "GK",
        "h_team": "Alaves",
        "a_team": "Valencia",
        "h_goals": "2",
        "a_goals": "1",
        "date": "2019-01-05",
        "id": "10127",
        "season": "2018",
        "roster_id": "309164",
        "xA": "0",
        "assists": "0",
        "key_passes": "0",
        "npg": "0",
        "npxG": "0",
        "xGChain": "0.15897226333618164",
        "xGBuildup": "0.15897226333618164"
    },
    {
        "goals": "0",
        "shots": "0",
        "xG": "0",
        "time": "90",
        "position": "GK",
        "h_team": "Valencia",
        "a_team": "SD Huesca",
        "h_goals": "2",
        "a_goals": "1",
        "date": "2018-12-23",
        "id": "10121",
        "season": "2018",
        "roster_id": "287884",
        "xA": "0",
        "assists": "0",
        "key_passes": "0",
        "npg": "0",
        "npxG": "0",
        "xGChain": "0",
        "xGBuildup": "0"
    },
    {
        "goals": "0",
        "shots": "0",
        "xG": "0",
        "time": "90",
        "position": "GK",
        "h_team": "Eibar",
        "a_team": "Valencia",
        "h_goals": "1",
        "a_goals": "1",
        "date": "2018-12-15",
        "id": "10114",
        "season": "2018",
        "roster_id": "287563",
        "xA": "0",
        "assists": "0",
        "key_passes": "0",
        "npg": "0",
        "npxG": "0",
        "xGChain": "0",
        "xGBuildup": "0"
    },
    {
        "goals": "0",
        "shots": "0",
        "xG": "0",
        "time": "90",
        "position": "GK",
        "h_team": "Valencia",
        "a_team": "Sevilla",
        "h_goals": "1",
        "a_goals": "1",
        "date": "2018-12-08",
        "id": "10106",
        "season": "2018",
        "roster_id": "287215",
        "xA": "0",
        "assists": "0",
        "key_passes": "0",
        "npg": "0",
        "npxG": "0",
        "xGChain": "0.056481294333934784",
        "xGBuildup": "0.056481294333934784"
    },
    {
        "goals": "0",
        "shots": "0",
        "xG": "0",
        "time": "90",
        "position": "GK",
        "h_team": "Real Madrid",
        "a_team": "Valencia",
        "h_goals": "2",
        "a_goals": "0",
        "date": "2018-12-01",
        "id": "10092",
        "season": "2018",
        "roster_id": "287008",
        "xA": "0",
        "assists": "0",
        "key_passes": "0",
        "npg": "0",
        "npxG": "0",
        "xGChain": "0.07491110265254974",
        "xGBuildup": "0.07491110265254974"
    },
    {
        "goals": "0",
        "shots": "0",
        "xG": "0",
        "time": "90",
        "position": "GK",
        "h_team": "Valencia",
        "a_team": "Rayo Vallecano",
        "h_goals": "3",
        "a_goals": "0",
        "date": "2018-11-24",
        "id": "10086",
        "season": "2018",
        "roster_id": "286659",
        "xA": "0",
        "assists": "0",
        "key_passes": "0",
        "npg": "0",
        "npxG": "0",
        "xGChain": "0",
        "xGBuildup": "0"
    },
    {
        "goals": "0",
        "shots": "0",
        "xG": "0",
        "time": "90",
        "position": "GK",
        "h_team": "Getafe",
        "a_team": "Valencia",
        "h_goals": "0",
        "a_goals": "1",
        "date": "2018-11-10",
        "id": "10073",
        "season": "2018",
        "roster_id": "286394",
        "xA": "0",
        "assists": "0",
        "key_passes": "0",
        "npg": "0",
        "npxG": "0",
        "xGChain": "0.26025673747062683",
        "xGBuildup": "0.26025673747062683"
    },
    {
        "goals": "0",
        "shots": "0",
        "xG": "0",
        "time": "90",
        "position": "GK",
        "h_team": "Valencia",
        "a_team": "Girona",
        "h_goals": "0",
        "a_goals": "1",
        "date": "2018-11-03",
        "id": "10058",
        "season": "2018",
        "roster_id": "286102",
        "xA": "0",
        "assists": "0",
        "key_passes": "0",
        "npg": "0",
        "npxG": "0",
        "xGChain": "0",
        "xGBuildup": "0"
    },
    {
        "goals": "0",
        "shots": "0",
        "xG": "0",
        "time": "90",
        "position": "GK",
        "h_team": "Athletic Club",
        "a_team": "Valencia",
        "h_goals": "0",
        "a_goals": "0",
        "date": "2018-10-27",
        "id": "10054",
        "season": "2018",
        "roster_id": "285839",
        "xA": "0",
        "assists": "0",
        "key_passes": "0",
        "npg": "0",
        "npxG": "0",
        "xGChain": "0.1328384429216385",
        "xGBuildup": "0.1328384429216385"
    },
    {
        "goals": "0",
        "shots": "0",
        "xG": "0",
        "time": "90",
        "position": "GK",
        "h_team": "Valencia",
        "a_team": "Leganes",
        "h_goals": "1",
        "a_goals": "1",
        "date": "2018-10-20",
        "id": "10038",
        "season": "2018",
        "roster_id": "285518",
        "xA": "0",
        "assists": "0",
        "key_passes": "0",
        "npg": "0",
        "npxG": "0",
        "xGChain": "0",
        "xGBuildup": "0"
    },
    {
        "goals": "0",
        "shots": "0",
        "xG": "0",
        "time": "90",
        "position": "GK",
        "h_team": "Valencia",
        "a_team": "Barcelona",
        "h_goals": "1",
        "a_goals": "1",
        "date": "2018-10-07",
        "id": "10030",
        "season": "2018",
        "roster_id": "285435",
        "xA": "0",
        "assists": "0",
        "key_passes": "0",
        "npg": "0",
        "npxG": "0",
        "xGChain": "0",
        "xGBuildup": "0"
    },
    {
        "goals": "0",
        "shots": "0",
        "xG": "0",
        "time": "90",
        "position": "GK",
        "h_team": "Real Sociedad",
        "a_team": "Valencia",
        "h_goals": "0",
        "a_goals": "1",
        "date": "2018-09-29",
        "id": "10023",
        "season": "2018",
        "roster_id": "253234",
        "xA": "0",
        "assists": "0",
        "key_passes": "0",
        "npg": "0",
        "npxG": "0",
        "xGChain": "0.06652198731899261",
        "xGBuildup": "0.06652198731899261"
    },
    {
        "goals": "0",
        "shots": "0",
        "xG": "0",
        "time": "90",
        "position": "GK",
        "h_team": "Valencia",
        "a_team": "Celta Vigo",
        "h_goals": "1",
        "a_goals": "1",
        "date": "2018-09-26",
        "id": "10011",
        "season": "2018",
        "roster_id": "252884",
        "xA": "0",
        "assists": "0",
        "key_passes": "0",
        "npg": "0",
        "npxG": "0",
        "xGChain": "0",
        "xGBuildup": "0"
    },
    {
        "goals": "0",
        "shots": "0",
        "xG": "0",
        "time": "90",
        "position": "GK",
        "h_team": "Villarreal",
        "a_team": "Valencia",
        "h_goals": "0",
        "a_goals": "0",
        "date": "2018-09-23",
        "id": "10006",
        "season": "2018",
        "roster_id": "251260",
        "xA": "0",
        "assists": "0",
        "key_passes": "0",
        "npg": "0",
        "npxG": "0",
        "xGChain": "0.042659588158130646",
        "xGBuildup": "0.042659588158130646"
    },
    {
        "goals": "0",
        "shots": "0",
        "xG": "0",
        "time": "90",
        "position": "GK",
        "h_team": "Levante",
        "a_team": "Valencia",
        "h_goals": "2",
        "a_goals": "2",
        "date": "2018-09-02",
        "id": "9983",
        "season": "2018",
        "roster_id": "247253",
        "xA": "0",
        "assists": "0",
        "key_passes": "0",
        "npg": "0",
        "npxG": "0",
        "xGChain": "0.3898700773715973",
        "xGBuildup": "0.3898700773715973"
    },
    {
        "goals": "0",
        "shots": "0",
        "xG": "0",
        "time": "90",
        "position": "GK",
        "h_team": "Espanyol",
        "a_team": "Valencia",
        "h_goals": "2",
        "a_goals": "0",
        "date": "2018-08-26",
        "id": "9972",
        "season": "2018",
        "roster_id": "245913",
        "xA": "0",
        "assists": "0",
        "key_passes": "0",
        "npg": "0",
        "npxG": "0",
        "xGChain": "0.3474283814430237",
        "xGBuildup": "0.3474283814430237"
    },
    {
        "goals": "0",
        "shots": "0",
        "xG": "0",
        "time": "90",
        "position": "GK",
        "h_team": "Valencia",
        "a_team": "Atletico Madrid",
        "h_goals": "1",
        "a_goals": "1",
        "date": "2018-08-20",
        "id": "9965",
        "season": "2018",
        "roster_id": "243733",
        "xA": "0",
        "assists": "0",
        "key_passes": "0",
        "npg": "0",
        "npxG": "0",
        "xGChain": "0.11495976150035858",
        "xGBuildup": "0.11495976150035858"
    },
    {
        "goals": "0",
        "shots": "0",
        "xG": "0",
        "time": "90",
        "position": "GK",
        "h_team": "Villarreal",
        "a_team": "Valencia",
        "h_goals": "1",
        "a_goals": "0",
        "date": "2018-05-05",
        "id": "8238",
        "season": "2017",
        "roster_id": "237776",
        "xA": "0",
        "assists": "0",
        "key_passes": "0",
        "npg": "0",
        "npxG": "0",
        "xGChain": "0",
        "xGBuildup": "0"
    },
    {
        "goals": "0",
        "shots": "0",
        "xG": "0",
        "time": "90",
        "position": "GK",
        "h_team": "Valencia",
        "a_team": "Eibar",
        "h_goals": "0",
        "a_goals": "0",
        "date": "2018-04-29",
        "id": "8219",
        "season": "2017",
        "roster_id": "236736",
        "xA": "0",
        "assists": "0",
        "key_passes": "0",
        "npg": "0",
        "npxG": "0",
        "xGChain": "0.018552055582404137",
        "xGBuildup": "0.018552055582404137"
    },
    {
        "goals": "0",
        "shots": "0",
        "xG": "0",
        "time": "90",
        "position": "GK",
        "h_team": "Celta Vigo",
        "a_team": "Valencia",
        "h_goals": "1",
        "a_goals": "1",
        "date": "2018-04-21",
        "id": "8218",
        "season": "2017",
        "roster_id": "234361",
        "xA": "0",
        "assists": "0",
        "key_passes": "0",
        "npg": "0",
        "npxG": "0",
        "xGChain": "0.47676897048950195",
        "xGBuildup": "0.47676897048950195"
    },
    {
        "goals": "0",
        "shots": "0",
        "xG": "0",
        "time": "90",
        "position": "GK",
        "h_team": "Barcelona",
        "a_team": "Valencia",
        "h_goals": "2",
        "a_goals": "1",
        "date": "2018-04-14",
        "id": "8197",
        "season": "2017",
        "roster_id": "232134",
        "xA": "0",
        "assists": "0",
        "key_passes": "0",
        "npg": "0",
        "npxG": "0",
        "xGChain": "0.1213204637169838",
        "xGBuildup": "0.1213204637169838"
    },
    {
        "goals": "0",
        "shots": "0",
        "xG": "0",
        "time": "90",
        "position": "GK",
        "h_team": "Valencia",
        "a_team": "Espanyol",
        "h_goals": "1",
        "a_goals": "0",
        "date": "2018-04-08",
        "id": "8183",
        "season": "2017",
        "roster_id": "231038",
        "xA": "0",
        "assists": "0",
        "key_passes": "0",
        "npg": "0",
        "npxG": "0",
        "xGChain": "0.40707656741142273",
        "xGBuildup": "0.40707656741142273"
    },
    {
        "goals": "0",
        "shots": "0",
        "xG": "0",
        "time": "90",
        "position": "GK",
        "h_team": "Valencia",
        "a_team": "Alaves",
        "h_goals": "3",
        "a_goals": "1",
        "date": "2018-03-17",
        "id": "8159",
        "season": "2017",
        "roster_id": "224011",
        "xA": "0",
        "assists": "0",
        "key_passes": "0",
        "npg": "0",
        "npxG": "0",
        "xGChain": "0.07087791711091995",
        "xGBuildup": "0.07087791711091995"
    },
    {
        "goals": "0",
        "shots": "0",
        "xG": "0",
        "time": "90",
        "position": "GK",
        "h_team": "Sevilla",
        "a_team": "Valencia",
        "h_goals": "0",
        "a_goals": "2",
        "date": "2018-03-10",
        "id": "8158",
        "season": "2017",
        "roster_id": "222414",
        "xA": "0",
        "assists": "0",
        "key_passes": "0",
        "npg": "0",
        "npxG": "0",
        "xGChain": "0.0744742751121521",
        "xGBuildup": "0.0744742751121521"
    },
    {
        "goals": "0",
        "shots": "0",
        "xG": "0",
        "time": "90",
        "position": "GK",
        "h_team": "Valencia",
        "a_team": "Real Betis",
        "h_goals": "2",
        "a_goals": "0",
        "date": "2018-03-04",
        "id": "8139",
        "season": "2017",
        "roster_id": "221794",
        "xA": "0",
        "assists": "0",
        "key_passes": "0",
        "npg": "0",
        "npxG": "0",
        "xGChain": "0",
        "xGBuildup": "0"
    },
    {
        "goals": "0",
        "shots": "0",
        "xG": "0",
        "time": "90",
        "position": "GK",
        "h_team": "Athletic Club",
        "a_team": "Valencia",
        "h_goals": "1",
        "a_goals": "1",
        "date": "2018-02-28",
        "id": "8136",
        "season": "2017",
        "roster_id": "220268",
        "xA": "0",
        "assists": "0",
        "key_passes": "0",
        "npg": "0",
        "npxG": "0",
        "xGChain": "0",
        "xGBuildup": "0"
    },
    {
        "goals": "0",
        "shots": "0",
        "xG": "0",
        "time": "90",
        "position": "GK",
        "h_team": "Valencia",
        "a_team": "Real Sociedad",
        "h_goals": "2",
        "a_goals": "1",
        "date": "2018-02-25",
        "id": "8119",
        "season": "2017",
        "roster_id": "219951",
        "xA": "0",
        "assists": "0",
        "key_passes": "0",
        "npg": "0",
        "npxG": "0",
        "xGChain": "0.07624504715204239",
        "xGBuildup": "0.07624504715204239"
    },
    {
        "goals": "0",
        "shots": "0",
        "xG": "0",
        "time": "90",
        "position": "GK",
        "h_team": "Malaga",
        "a_team": "Valencia",
        "h_goals": "1",
        "a_goals": "2",
        "date": "2018-02-17",
        "id": "8116",
        "season": "2017",
        "roster_id": "218250",
        "xA": "0",
        "assists": "0",
        "key_passes": "0",
        "npg": "0",
        "npxG": "0",
        "xGChain": "0",
        "xGBuildup": "0"
    },
    {
        "goals": "0",
        "shots": "0",
        "xG": "0",
        "time": "90",
        "position": "GK",
        "h_team": "Valencia",
        "a_team": "Levante",
        "h_goals": "3",
        "a_goals": "1",
        "date": "2018-02-11",
        "id": "8099",
        "season": "2017",
        "roster_id": "216784",
        "xA": "0",
        "assists": "0",
        "key_passes": "0",
        "npg": "0",
        "npxG": "0",
        "xGChain": "0.1455339938402176",
        "xGBuildup": "0.1455339938402176"
    },
    {
        "goals": "0",
        "shots": "0",
        "xG": "0",
        "time": "90",
        "position": "GK",
        "h_team": "Atletico Madrid",
        "a_team": "Valencia",
        "h_goals": "1",
        "a_goals": "0",
        "date": "2018-02-04",
        "id": "8098",
        "season": "2017",
        "roster_id": "216771",
        "xA": "0",
        "assists": "0",
        "key_passes": "0",
        "npg": "0",
        "npxG": "0",
        "xGChain": "0.031544655561447144",
        "xGBuildup": "0.031544655561447144"
    },
    {
        "goals": "0",
        "shots": "0",
        "xG": "0",
        "time": "90",
        "position": "GK",
        "h_team": "Valencia",
        "a_team": "Real Madrid",
        "h_goals": "1",
        "a_goals": "4",
        "date": "2018-01-27",
        "id": "8088",
        "season": "2017",
        "roster_id": "210551",
        "xA": "0",
        "assists": "0",
        "key_passes": "0",
        "npg": "0",
        "npxG": "0",
        "xGChain": "0.16819535195827484",
        "xGBuildup": "0.16819535195827484"
    },
    {
        "goals": "0",
        "shots": "0",
        "xG": "0",
        "time": "90",
        "position": "GK",
        "h_team": "Las Palmas",
        "a_team": "Valencia",
        "h_goals": "2",
        "a_goals": "1",
        "date": "2018-01-20",
        "id": "8069",
        "season": "2017",
        "roster_id": "209567",
        "xA": "0",
        "assists": "0",
        "key_passes": "0",
        "npg": "0",
        "npxG": "0",
        "xGChain": "0.037730805575847626",
        "xGBuildup": "0.037730805575847626"
    },
    {
        "goals": "0",
        "shots": "0",
        "xG": "0",
        "time": "90",
        "position": "GK",
        "h_team": "Deportivo La Coruna",
        "a_team": "Valencia",
        "h_goals": "1",
        "a_goals": "2",
        "date": "2018-01-13",
        "id": "8061",
        "season": "2017",
        "roster_id": "208080",
        "xA": "0",
        "assists": "0",
        "key_passes": "0",
        "npg": "0",
        "npxG": "0",
        "xGChain": "0",
        "xGBuildup": "0"
    },
    {
        "goals": "0",
        "shots": "0",
        "xG": "0",
        "time": "90",
        "position": "GK",
        "h_team": "Valencia",
        "a_team": "Girona",
        "h_goals": "2",
        "a_goals": "1",
        "date": "2018-01-06",
        "id": "8058",
        "season": "2017",
        "roster_id": "207017",
        "xA": "0",
        "assists": "0",
        "key_passes": "0",
        "npg": "0",
        "npxG": "0",
        "xGChain": "0",
        "xGBuildup": "0"
    },
    {
        "goals": "0",
        "shots": "1",
        "xG": "0.4786851406097412",
        "time": "90",
        "position": "GK",
        "h_team": "Valencia",
        "a_team": "Villarreal",
        "h_goals": "0",
        "a_goals": "1",
        "date": "2017-12-23",
        "id": "8048",
        "season": "2017",
        "roster_id": "204667",
        "xA": "0",
        "assists": "0",
        "key_passes": "0",
        "npg": "0",
        "npxG": "0.4786851406097412",
        "xGChain": "0",
        "xGBuildup": "0"
    },
    {
        "goals": "0",
        "shots": "0",
        "xG": "0",
        "time": "90",
        "position": "GK",
        "h_team": "Eibar",
        "a_team": "Valencia",
        "h_goals": "2",
        "a_goals": "1",
        "date": "2017-12-16",
        "id": "8031",
        "season": "2017",
        "roster_id": "204321",
        "xA": "0",
        "assists": "0",
        "key_passes": "0",
        "npg": "0",
        "npxG": "0",
        "xGChain": "0",
        "xGBuildup": "0"
    },
    {
        "goals": "0",
        "shots": "0",
        "xG": "0",
        "time": "90",
        "position": "GK",
        "h_team": "Valencia",
        "a_team": "Celta Vigo",
        "h_goals": "2",
        "a_goals": "1",
        "date": "2017-12-09",
        "id": "8028",
        "season": "2017",
        "roster_id": "200064",
        "xA": "0",
        "assists": "0",
        "key_passes": "0",
        "npg": "0",
        "npxG": "0",
        "xGChain": "0.07349807024002075",
        "xGBuildup": "0.07349807024002075"
    },
    {
        "goals": "0",
        "shots": "0",
        "xG": "0",
        "time": "90",
        "position": "GK",
        "h_team": "Getafe",
        "a_team": "Valencia",
        "h_goals": "1",
        "a_goals": "0",
        "date": "2017-12-03",
        "id": "8009",
        "season": "2017",
        "roster_id": "190769",
        "xA": "0",
        "assists": "0",
        "key_passes": "0",
        "npg": "0",
        "npxG": "0",
        "xGChain": "0",
        "xGBuildup": "0"
    },
    {
        "goals": "0",
        "shots": "0",
        "xG": "0",
        "time": "90",
        "position": "GK",
        "h_team": "Valencia",
        "a_team": "Barcelona",
        "h_goals": "1",
        "a_goals": "1",
        "date": "2017-11-26",
        "id": "8008",
        "season": "2017",
        "roster_id": "190700",
        "xA": "0",
        "assists": "0",
        "key_passes": "0",
        "npg": "0",
        "npxG": "0",
        "xGChain": "0.12064953148365021",
        "xGBuildup": "0.12064953148365021"
    },
    {
        "goals": "0",
        "shots": "0",
        "xG": "0",
        "time": "90",
        "position": "GK",
        "h_team": "Espanyol",
        "a_team": "Valencia",
        "h_goals": "0",
        "a_goals": "2",
        "date": "2017-11-19",
        "id": "7989",
        "season": "2017",
        "roster_id": "191428",
        "xA": "0",
        "assists": "0",
        "key_passes": "0",
        "npg": "0",
        "npxG": "0",
        "xGChain": "0",
        "xGBuildup": "0"
    },
    {
        "goals": "0",
        "shots": "0",
        "xG": "0",
        "time": "90",
        "position": "GK",
        "h_team": "Valencia",
        "a_team": "Leganes",
        "h_goals": "3",
        "a_goals": "0",
        "date": "2017-11-04",
        "id": "7988",
        "season": "2017",
        "roster_id": "191387",
        "xA": "0",
        "assists": "0",
        "key_passes": "0",
        "npg": "0",
        "npxG": "0",
        "xGChain": "0.07316632568836212",
        "xGBuildup": "0.07316632568836212"
    },
    {
        "goals": "0",
        "shots": "0",
        "xG": "0",
        "time": "90",
        "position": "GK",
        "h_team": "Alaves",
        "a_team": "Valencia",
        "h_goals": "1",
        "a_goals": "2",
        "date": "2017-10-28",
        "id": "7969",
        "season": "2017",
        "roster_id": "190464",
        "xA": "0",
        "assists": "0",
        "key_passes": "0",
        "npg": "0",
        "npxG": "0",
        "xGChain": "0",
        "xGBuildup": "0"
    },
    {
        "goals": "0",
        "shots": "0",
        "xG": "0",
        "time": "90",
        "position": "GK",
        "h_team": "Valencia",
        "a_team": "Sevilla",
        "h_goals": "4",
        "a_goals": "0",
        "date": "2017-10-21",
        "id": "7964",
        "season": "2017",
        "roster_id": "190395",
        "xA": "0",
        "assists": "0",
        "key_passes": "0",
        "npg": "0",
        "npxG": "0",
        "xGChain": "0",
        "xGBuildup": "0"
    },
    {
        "goals": "0",
        "shots": "0",
        "xG": "0",
        "time": "90",
        "position": "GK",
        "h_team": "Real Betis",
        "a_team": "Valencia",
        "h_goals": "3",
        "a_goals": "6",
        "date": "2017-10-15",
        "id": "7949",
        "season": "2017",
        "roster_id": "190271",
        "xA": "0",
        "assists": "0",
        "key_passes": "0",
        "npg": "0",
        "npxG": "0",
        "xGChain": "0.03762875497341156",
        "xGBuildup": "0.03762875497341156"
    },
    {
        "goals": "0",
        "shots": "0",
        "xG": "0",
        "time": "90",
        "position": "GK",
        "h_team": "Valencia",
        "a_team": "Athletic Club",
        "h_goals": "3",
        "a_goals": "2",
        "date": "2017-10-01",
        "id": "7948",
        "season": "2017",
        "roster_id": "190203",
        "xA": "0",
        "assists": "0",
        "key_passes": "0",
        "npg": "0",
        "npxG": "0",
        "xGChain": "0.3074057698249817",
        "xGBuildup": "0.3074057698249817"
    },
    {
        "goals": "0",
        "shots": "0",
        "xG": "0",
        "time": "90",
        "position": "GK",
        "h_team": "Valencia",
        "a_team": "Malaga",
        "h_goals": "5",
        "a_goals": "0",
        "date": "2017-09-19",
        "id": "7928",
        "season": "2017",
        "roster_id": "189199",
        "xA": "0",
        "assists": "0",
        "key_passes": "0",
        "npg": "0",
        "npxG": "0",
        "xGChain": "0.1442641317844391",
        "xGBuildup": "0.1442641317844391"
    },
    {
        "goals": "0",
        "shots": "0",
        "xG": "0",
        "time": "90",
        "position": "GK",
        "h_team": "Levante",
        "a_team": "Valencia",
        "h_goals": "1",
        "a_goals": "1",
        "date": "2017-09-16",
        "id": "7909",
        "season": "2017",
        "roster_id": "188684",
        "xA": "0",
        "assists": "0",
        "key_passes": "0",
        "npg": "0",
        "npxG": "0",
        "xGChain": "0.38346919417381287",
        "xGBuildup": "0.38346919417381287"
    },
    {
        "goals": "0",
        "shots": "0",
        "xG": "0",
        "time": "90",
        "position": "GK",
        "h_team": "Valencia",
        "a_team": "Atletico Madrid",
        "h_goals": "0",
        "a_goals": "0",
        "date": "2017-09-09",
        "id": "7908",
        "season": "2017",
        "roster_id": "188642",
        "xA": "0",
        "assists": "0",
        "key_passes": "0",
        "npg": "0",
        "npxG": "0",
        "xGChain": "0.02125832438468933",
        "xGBuildup": "0.02125832438468933"
    },
    {
        "goals": "0",
        "shots": "0",
        "xG": "0",
        "time": "90",
        "position": "GK",
        "h_team": "Real Madrid",
        "a_team": "Valencia",
        "h_goals": "2",
        "a_goals": "2",
        "date": "2017-08-27",
        "id": "7897",
        "season": "2017",
        "roster_id": "188125",
        "xA": "0",
        "assists": "0",
        "key_passes": "0",
        "npg": "0",
        "npxG": "0",
        "xGChain": "0",
        "xGBuildup": "0"
    },
    {
        "goals": "0",
        "shots": "0",
        "xG": "0",
        "time": "90",
        "position": "GK",
        "h_team": "Valencia",
        "a_team": "Las Palmas",
        "h_goals": "1",
        "a_goals": "0",
        "date": "2017-08-18",
        "id": "7880",
        "season": "2017",
        "roster_id": "187999",
        "xA": "0",
        "assists": "0",
        "key_passes": "0",
        "npg": "0",
        "npxG": "0",
        "xGChain": "0.048983924090862274",
        "xGBuildup": "0.048983924090862274"
    },
    {
        "goals": "0",
        "shots": "0",
        "xG": "0",
        "time": "90",
        "position": "GK",
        "h_team": "Juventus",
        "a_team": "Torino",
        "h_goals": "1",
        "a_goals": "1",
        "date": "2017-05-06",
        "id": "3691",
        "season": "2016",
        "roster_id": "169912",
        "xA": "0",
        "assists": "0",
        "key_passes": "0",
        "npg": "0",
        "npxG": "0",
        "xGChain": "0.04730723798274994",
        "xGBuildup": "0.04730723798274994"
    },
    {
        "goals": "0",
        "shots": "0",
        "xG": "0",
        "time": "90",
        "position": "GK",
        "h_team": "Juventus",
        "a_team": "Genoa",
        "h_goals": "4",
        "a_goals": "0",
        "date": "2017-04-23",
        "id": "3666",
        "season": "2016",
        "roster_id": "168659",
        "xA": "0",
        "assists": "0",
        "key_passes": "0",
        "npg": "0",
        "npxG": "0",
        "xGChain": "0.08865121752023697",
        "xGBuildup": "0.08865121752023697"
    },
    {
        "goals": "0",
        "shots": "0",
        "xG": "0",
        "time": "90",
        "position": "GK",
        "h_team": "Pescara",
        "a_team": "Juventus",
        "h_goals": "0",
        "a_goals": "2",
        "date": "2017-04-15",
        "id": "3657",
        "season": "2016",
        "roster_id": "168141",
        "xA": "0",
        "assists": "0",
        "key_passes": "0",
        "npg": "0",
        "npxG": "0",
        "xGChain": "0.35111188888549805",
        "xGBuildup": "0.35111188888549805"
    },
    {
        "goals": "0",
        "shots": "0",
        "xG": "0",
        "time": "90",
        "position": "GK",
        "h_team": "Juventus",
        "a_team": "Empoli",
        "h_goals": "2",
        "a_goals": "0",
        "date": "2017-02-25",
        "id": "3595",
        "season": "2016",
        "roster_id": "164524",
        "xA": "0",
        "assists": "0",
        "key_passes": "0",
        "npg": "0",
        "npxG": "0",
        "xGChain": "0.2619594931602478",
        "xGBuildup": "0.2619594931602478"
    },
    {
        "goals": "0",
        "shots": "0",
        "xG": "0",
        "time": "90",
        "position": "GK",
        "h_team": "Juventus",
        "a_team": "Bologna",
        "h_goals": "3",
        "a_goals": "0",
        "date": "2017-01-08",
        "id": "3529",
        "season": "2016",
        "roster_id": "171140",
        "xA": "0",
        "assists": "0",
        "key_passes": "0",
        "npg": "0",
        "npxG": "0",
        "xGChain": "0.5552590489387512",
        "xGBuildup": "0.5552590489387512"
    },
    {
        "goals": "0",
        "shots": "0",
        "xG": "0",
        "time": "90",
        "position": "GK",
        "h_team": "Juventus",
        "a_team": "Pescara",
        "h_goals": "3",
        "a_goals": "0",
        "date": "2016-11-19",
        "id": "2758",
        "season": "2016",
        "roster_id": "167847",
        "xA": "0",
        "assists": "0",
        "key_passes": "0",
        "npg": "0",
        "npxG": "0",
        "xGChain": "0",
        "xGBuildup": "0"
    },
    {
        "goals": "0",
        "shots": "0",
        "xG": "0",
        "time": "90",
        "position": "GK",
        "h_team": "Juventus",
        "a_team": "Sampdoria",
        "h_goals": "4",
        "a_goals": "1",
        "date": "2016-10-26",
        "id": "3282",
        "season": "2016",
        "roster_id": "166141",
        "xA": "0",
        "assists": "0",
        "key_passes": "0",
        "npg": "0",
        "npxG": "0",
        "xGChain": "0.1808653324842453",
        "xGBuildup": "0.1808653324842453"
    },
    {
        "goals": "0",
        "shots": "0",
        "xG": "0",
        "time": "44",
        "position": "Sub",
        "h_team": "Juventus",
        "a_team": "Cagliari",
        "h_goals": "4",
        "a_goals": "0",
        "date": "2016-09-21",
        "id": "975",
        "season": "2016",
        "roster_id": "163390",
        "xA": "0",
        "assists": "0",
        "key_passes": "0",
        "npg": "0",
        "npxG": "0",
        "xGChain": "0",
        "xGBuildup": "0"
    },
    {
        "goals": "0",
        "shots": "0",
        "xG": "0",
        "time": "90",
        "position": "GK",
        "h_team": "Juventus",
        "a_team": "Sampdoria",
        "h_goals": "5",
        "a_goals": "0",
        "date": "2016-05-14",
        "id": "921",
        "season": "2015",
        "roster_id": "114304",
        "xA": "0",
        "assists": "0",
        "key_passes": "0",
        "npg": "0",
        "npxG": "0",
        "xGChain": "0.008673588745296001",
        "xGBuildup": "0.008673588745296001"
    },
    {
        "goals": "0",
        "shots": "0",
        "xG": "0",
        "time": "90",
        "position": "GK",
        "h_team": "Verona",
        "a_team": "Juventus",
        "h_goals": "2",
        "a_goals": "1",
        "date": "2016-05-08",
        "id": "920",
        "season": "2015",
        "roster_id": "113620",
        "xA": "0",
        "assists": "0",
        "key_passes": "0",
        "npg": "0",
        "npxG": "0",
        "xGChain": "0",
        "xGBuildup": "0"
    },
    {
        "goals": "0",
        "shots": "0",
        "xG": "0",
        "time": "90",
        "position": "GK",
        "h_team": "Juventus",
        "a_team": "Frosinone",
        "h_goals": "1",
        "a_goals": "1",
        "date": "2015-09-23",
        "id": "599",
        "season": "2015",
        "roster_id": "106528",
        "xA": "0",
        "assists": "0",
        "key_passes": "0",
        "npg": "0",
        "npxG": "0",
        "xGChain": "0.11172851175069809",
        "xGBuildup": "0.11172851175069809"
    },
    {
        "goals": "0",
        "shots": "0",
        "xG": "0",
        "time": "90",
        "position": "GK",
        "h_team": "Palermo",
        "a_team": "Fiorentina",
        "h_goals": "2",
        "a_goals": "3",
        "date": "2015-05-24",
        "id": "4814",
        "season": "2014",
        "roster_id": "56564",
        "xA": "0",
        "assists": "0",
        "key_passes": "0",
        "npg": "0",
        "npxG": "0",
        "xGChain": "0.12195000797510147",
        "xGBuildup": "0.12195000797510147"
    },
    {
        "goals": "0",
        "shots": "0",
        "xG": "0",
        "time": "90",
        "position": "GK",
        "h_team": "Fiorentina",
        "a_team": "Parma",
        "h_goals": "3",
        "a_goals": "0",
        "date": "2015-05-18",
        "id": "4807",
        "season": "2014",
        "roster_id": "56076",
        "xA": "0",
        "assists": "0",
        "key_passes": "0",
        "npg": "0",
        "npxG": "0",
        "xGChain": "0.22370341420173645",
        "xGBuildup": "0.22370341420173645"
    },
    {
        "goals": "0",
        "shots": "0",
        "xG": "0",
        "time": "90",
        "position": "GK",
        "h_team": "Empoli",
        "a_team": "Fiorentina",
        "h_goals": "2",
        "a_goals": "3",
        "date": "2015-05-10",
        "id": "4796",
        "season": "2014",
        "roster_id": "56173",
        "xA": "0",
        "assists": "0",
        "key_passes": "0",
        "npg": "0",
        "npxG": "0",
        "xGChain": "0",
        "xGBuildup": "0"
    },
    {
        "goals": "0",
        "shots": "0",
        "xG": "0",
        "time": "90",
        "position": "GK",
        "h_team": "Fiorentina",
        "a_team": "Cesena",
        "h_goals": "3",
        "a_goals": "1",
        "date": "2015-05-03",
        "id": "4785",
        "season": "2014",
        "roster_id": "56718",
        "xA": "0.10236965864896774",
        "assists": "0",
        "key_passes": "1",
        "npg": "0",
        "npxG": "0",
        "xGChain": "0.16069874167442322",
        "xGBuildup": "0.05832908675074577"
    },
    {
        "goals": "0",
        "shots": "0",
        "xG": "0",
        "time": "90",
        "position": "GK",
        "h_team": "Juventus",
        "a_team": "Fiorentina",
        "h_goals": "3",
        "a_goals": "2",
        "date": "2015-04-29",
        "id": "4877",
        "season": "2014",
        "roster_id": "55783",
        "xA": "0",
        "assists": "0",
        "key_passes": "0",
        "npg": "0",
        "npxG": "0",
        "xGChain": "0.09154090285301208",
        "xGBuildup": "0.09154090285301208"
    },
    {
        "goals": "0",
        "shots": "0",
        "xG": "0",
        "time": "90",
        "position": "GK",
        "h_team": "Fiorentina",
        "a_team": "Cagliari",
        "h_goals": "1",
        "a_goals": "3",
        "date": "2015-04-26",
        "id": "4869",
        "season": "2014",
        "roster_id": "55127",
        "xA": "0",
        "assists": "0",
        "key_passes": "0",
        "npg": "0",
        "npxG": "0",
        "xGChain": "0",
        "xGBuildup": "0"
    },
    {
        "goals": "0",
        "shots": "0",
        "xG": "0",
        "time": "90",
        "position": "GK",
        "h_team": "Fiorentina",
        "a_team": "Verona",
        "h_goals": "0",
        "a_goals": "1",
        "date": "2015-04-20",
        "id": "4860",
        "season": "2014",
        "roster_id": "54765",
        "xA": "0",
        "assists": "0",
        "key_passes": "0",
        "npg": "0",
        "npxG": "0",
        "xGChain": "0.0965193584561348",
        "xGBuildup": "0.0965193584561348"
    },
    {
        "goals": "0",
        "shots": "0",
        "xG": "0",
        "time": "90",
        "position": "GK",
        "h_team": "Napoli",
        "a_team": "Fiorentina",
        "h_goals": "3",
        "a_goals": "0",
        "date": "2015-04-12",
        "id": "4845",
        "season": "2014",
        "roster_id": "54222",
        "xA": "0",
        "assists": "0",
        "key_passes": "0",
        "npg": "0",
        "npxG": "0",
        "xGChain": "0",
        "xGBuildup": "0"
    },
    {
        "goals": "0",
        "shots": "0",
        "xG": "0",
        "time": "90",
        "position": "GK",
        "h_team": "Fiorentina",
        "a_team": "Sampdoria",
        "h_goals": "2",
        "a_goals": "0",
        "date": "2015-04-04",
        "id": "4837",
        "season": "2014",
        "roster_id": "53873",
        "xA": "0",
        "assists": "0",
        "key_passes": "0",
        "npg": "0",
        "npxG": "0",
        "xGChain": "0.42386823892593384",
        "xGBuildup": "0.42386823892593384"
    },
    {
        "goals": "0",
        "shots": "0",
        "xG": "0",
        "time": "90",
        "position": "GK",
        "h_team": "Udinese",
        "a_team": "Fiorentina",
        "h_goals": "2",
        "a_goals": "2",
        "date": "2015-03-22",
        "id": "4916",
        "season": "2014",
        "roster_id": "54585",
        "xA": "0",
        "assists": "0",
        "key_passes": "0",
        "npg": "0",
        "npxG": "0",
        "xGChain": "0.15478086471557617",
        "xGBuildup": "0.15478086471557617"
    },
    {
        "goals": "0",
        "shots": "0",
        "xG": "0",
        "time": "90",
        "position": "GK",
        "h_team": "Fiorentina",
        "a_team": "AC Milan",
        "h_goals": "2",
        "a_goals": "1",
        "date": "2015-03-16",
        "id": "4907",
        "season": "2014",
        "roster_id": "54180",
        "xA": "0",
        "assists": "0",
        "key_passes": "0",
        "npg": "0",
        "npxG": "0",
        "xGChain": "0",
        "xGBuildup": "0"
    },
    {
        "goals": "0",
        "shots": "0",
        "xG": "0",
        "time": "90",
        "position": "GK",
        "h_team": "Lazio",
        "a_team": "Fiorentina",
        "h_goals": "4",
        "a_goals": "0",
        "date": "2015-03-09",
        "id": "4897",
        "season": "2014",
        "roster_id": "53496",
        "xA": "0",
        "assists": "0",
        "key_passes": "0",
        "npg": "0",
        "npxG": "0",
        "xGChain": "0",
        "xGBuildup": "0"
    },
    {
        "goals": "0",
        "shots": "0",
        "xG": "0",
        "time": "90",
        "position": "GK",
        "h_team": "Inter",
        "a_team": "Fiorentina",
        "h_goals": "0",
        "a_goals": "1",
        "date": "2015-03-01",
        "id": "4886",
        "season": "2014",
        "roster_id": "52884",
        "xA": "0",
        "assists": "0",
        "key_passes": "0",
        "npg": "0",
        "npxG": "0",
        "xGChain": "0.07219450920820236",
        "xGBuildup": "0.07219450920820236"
    },
    {
        "goals": "0",
        "shots": "0",
        "xG": "0",
        "time": "90",
        "position": "GK",
        "h_team": "Fiorentina",
        "a_team": "Empoli",
        "h_goals": "1",
        "a_goals": "1",
        "date": "2014-12-21",
        "id": "5026",
        "season": "2014",
        "roster_id": "50733",
        "xA": "0",
        "assists": "0",
        "key_passes": "0",
        "npg": "0",
        "npxG": "0",
        "xGChain": "0.30047014355659485",
        "xGBuildup": "0.30047014355659485"
    },
    {
        "goals": "0",
        "shots": "0",
        "xG": "0",
        "time": "90",
        "position": "GK",
        "h_team": "Cesena",
        "a_team": "Fiorentina",
        "h_goals": "1",
        "a_goals": "4",
        "date": "2014-12-14",
        "id": "5016",
        "season": "2014",
        "roster_id": "50413",
        "xA": "0",
        "assists": "0",
        "key_passes": "0",
        "npg": "0",
        "npxG": "0",
        "xGChain": "0",
        "xGBuildup": "0"
    },
    {
        "goals": "0",
        "shots": "0",
        "xG": "0",
        "time": "90",
        "position": "GK",
        "h_team": "Fiorentina",
        "a_team": "Juventus",
        "h_goals": "0",
        "a_goals": "0",
        "date": "2014-12-05",
        "id": "5000",
        "season": "2014",
        "roster_id": "50176",
        "xA": "0",
        "assists": "0",
        "key_passes": "0",
        "npg": "0",
        "npxG": "0",
        "xGChain": "0",
        "xGBuildup": "0"
    },
    {
        "goals": "0",
        "shots": "0",
        "xG": "0",
        "time": "90",
        "position": "GK",
        "h_team": "Cagliari",
        "a_team": "Fiorentina",
        "h_goals": "0",
        "a_goals": "4",
        "date": "2014-11-30",
        "id": "5065",
        "season": "2014",
        "roster_id": "49854",
        "xA": "0",
        "assists": "0",
        "key_passes": "0",
        "npg": "0",
        "npxG": "0",
        "xGChain": "0.04325253143906593",
        "xGBuildup": "0.04325253143906593"
    },
    {
        "goals": "0",
        "shots": "0",
        "xG": "0",
        "time": "90",
        "position": "GK",
        "h_team": "Verona",
        "a_team": "Fiorentina",
        "h_goals": "1",
        "a_goals": "2",
        "date": "2014-11-23",
        "id": "5057",
        "season": "2014",
        "roster_id": "49660",
        "xA": "0",
        "assists": "0",
        "key_passes": "0",
        "npg": "0",
        "npxG": "0",
        "xGChain": "0.9508112072944641",
        "xGBuildup": "0.9508112072944641"
    },
    {
        "goals": "0",
        "shots": "0",
        "xG": "0",
        "time": "90",
        "position": "GK",
        "h_team": "Fiorentina",
        "a_team": "Napoli",
        "h_goals": "0",
        "a_goals": "1",
        "date": "2014-11-09",
        "id": "5047",
        "season": "2014",
        "roster_id": "49369",
        "xA": "0",
        "assists": "0",
        "key_passes": "0",
        "npg": "0",
        "npxG": "0",
        "xGChain": "0.026672298088669777",
        "xGBuildup": "0.026672298088669777"
    },
    {
        "goals": "0",
        "shots": "0",
        "xG": "0",
        "time": "90",
        "position": "GK",
        "h_team": "Sampdoria",
        "a_team": "Fiorentina",
        "h_goals": "3",
        "a_goals": "1",
        "date": "2014-11-02",
        "id": "5033",
        "season": "2014",
        "roster_id": "49216",
        "xA": "0",
        "assists": "0",
        "key_passes": "0",
        "npg": "0",
        "npxG": "0",
        "xGChain": "0.08357812464237213",
        "xGBuildup": "0.08357812464237213"
    },
    {
        "goals": "0",
        "shots": "0",
        "xG": "0",
        "time": "90",
        "position": "GK",
        "h_team": "Fiorentina",
        "a_team": "Udinese",
        "h_goals": "3",
        "a_goals": "0",
        "date": "2014-10-29",
        "id": "5106",
        "season": "2014",
        "roster_id": "48784",
        "xA": "0.04322030767798424",
        "assists": "0",
        "key_passes": "1",
        "npg": "0",
        "npxG": "0",
        "xGChain": "0.03759131580591202",
        "xGBuildup": "0.03759131580591202"
    },
    {
        "goals": "0",
        "shots": "0",
        "xG": "0",
        "time": "90",
        "position": "GK",
        "h_team": "AC Milan",
        "a_team": "Fiorentina",
        "h_goals": "1",
        "a_goals": "1",
        "date": "2014-10-26",
        "id": "5098",
        "season": "2014",
        "roster_id": "48602",
        "xA": "0",
        "assists": "0",
        "key_passes": "0",
        "npg": "0",
        "npxG": "0",
        "xGChain": "0.015527503564953804",
        "xGBuildup": "0.015527503564953804"
    },
    {
        "goals": "0",
        "shots": "0",
        "xG": "0",
        "time": "90",
        "position": "GK",
        "h_team": "Fiorentina",
        "a_team": "Lazio",
        "h_goals": "0",
        "a_goals": "2",
        "date": "2014-10-19",
        "id": "5081",
        "season": "2014",
        "roster_id": "48227",
        "xA": "0",
        "assists": "0",
        "key_passes": "0",
        "npg": "0",
        "npxG": "0",
        "xGChain": "0.024473557248711586",
        "xGBuildup": "0.024473557248711586"
    },
    {
        "goals": "0",
        "shots": "0",
        "xG": "0",
        "time": "90",
        "position": "GK",
        "h_team": "Fiorentina",
        "a_team": "Inter",
        "h_goals": "3",
        "a_goals": "0",
        "date": "2014-10-05",
        "id": "5077",
        "season": "2014",
        "roster_id": "47919",
        "xA": "0",
        "assists": "0",
        "key_passes": "0",
        "npg": "0",
        "npxG": "0",
        "xGChain": "0.0175294429063797",
        "xGBuildup": "0.0175294429063797"
    },
    {
        "goals": "0",
        "shots": "0",
        "xG": "0",
        "time": "90",
        "position": "GK",
        "h_team": "Torino",
        "a_team": "Fiorentina",
        "h_goals": "1",
        "a_goals": "1",
        "date": "2014-09-28",
        "id": "5142",
        "season": "2014",
        "roster_id": "47849",
        "xA": "0",
        "assists": "0",
        "key_passes": "0",
        "npg": "0",
        "npxG": "0",
        "xGChain": "0.021181175485253334",
        "xGBuildup": "0.021181175485253334"
    },
    {
        "goals": "0",
        "shots": "0",
        "xG": "0",
        "time": "90",
        "position": "GK",
        "h_team": "Fiorentina",
        "a_team": "Sassuolo",
        "h_goals": "0",
        "a_goals": "0",
        "date": "2014-09-24",
        "id": "5130",
        "season": "2014",
        "roster_id": "47387",
        "xA": "0",
        "assists": "0",
        "key_passes": "0",
        "npg": "0",
        "npxG": "0",
        "xGChain": "0.04381295666098595",
        "xGBuildup": "0.04381295666098595"
    },
    {
        "goals": "0",
        "shots": "0",
        "xG": "0",
        "time": "90",
        "position": "GK",
        "h_team": "Atalanta",
        "a_team": "Fiorentina",
        "h_goals": "0",
        "a_goals": "1",
        "date": "2014-09-21",
        "id": "5126",
        "season": "2014",
        "roster_id": "47067",
        "xA": "0",
        "assists": "0",
        "key_passes": "0",
        "npg": "0",
        "npxG": "0",
        "xGChain": "0.0431642010807991",
        "xGBuildup": "0.0431642010807991"
    },
    {
        "goals": "0",
        "shots": "0",
        "xG": "0",
        "time": "90",
        "position": "GK",
        "h_team": "Fiorentina",
        "a_team": "Genoa",
        "h_goals": "0",
        "a_goals": "0",
        "date": "2014-09-14",
        "id": "5114",
        "season": "2014",
        "roster_id": "46829",
        "xA": "0",
        "assists": "0",
        "key_passes": "0",
        "npg": "0",
        "npxG": "0",
        "xGChain": "0.010766646824777126",
        "xGBuildup": "0.010766646824777126"
    },
    {
        "goals": "0",
        "shots": "0",
        "xG": "0",
        "time": "90",
        "position": "GK",
        "h_team": "Roma",
        "a_team": "Fiorentina",
        "h_goals": "2",
        "a_goals": "0",
        "date": "2014-08-30",
        "id": "5150",
        "season": "2014",
        "roster_id": "46676",
        "xA": "0",
        "assists": "0",
        "key_passes": "0",
        "npg": "0",
        "npxG": "0",
        "xGChain": "0.008830074220895767",
        "xGBuildup": "0.008830074220895767"
    }
]